Workbook

Sheet Weekly Stats
A1: UNCVRD — WEEKLY STATS
A2: From ▸ | B2: 46199 | C2: To ▸ | D2: 46205 | E2: Creator ▸ | F2: All | H2: =TEXT($B$2,"mmm d")&" → "&TEXT($D$2,"mmm d")&" (pick any dates — set From=To for a single day)"
A3: Sheet ID ▸ | D3: Spend = Clicks × the CPC you type per platform (yellow cells in the CPC column). Paste sheet ID for day-by-day manual overrides.
A4: Metrics i need to know | B4: Clicks | C4: Fans | D4: Spend | E4: CAC | F4: CPC | G4: CVR | H4: Attributed Revenue | I4: Total LTV 48h | J4: Total LTV 7d | K4: Total LTV 14d | L4: Total LTV 30d | M4: ROAS | N4: Agency Profit
A5: Meta | B5: =SUMIFS(Data!$D:$D,Data!$A:$A,">="&$B$2,Data!$A:$A,"<="&$D$2,Data!$C:$C,"Meta",Data!$B:$B,IF($F$2="All","*",$F$2)) | C5: =SUMIFS(Data!$E:$E,Data!$A:$A,">="&$B$2,Data!$A:$A,"<="&$D$2,Data!$C:$C,"Meta",Data!$B:$B,IF($F$2="All","*",$F$2)) | D5: =B5*F5 | E5: =IFERROR(D5/C5,"") | F5: 0.75 | G5: =IFERROR(C5/B5,"") | H5: =SUMIFS(Data!$G:$G,Data!$A:$A,">="&$B$2,Data!$A:$A,"<="&$D$2,Data!$C:$C,"Meta",Data!$B:$B,IF($F$2="All","*",$F$2)) | I5: =IFERROR(SUMIFS(Cohort!$E:$E,Cohort!$B:$B,"Meta",Cohort!$A:$A,IF($F$2="All","*",$F$2))/SUMIFS(Cohort!$C:$C,Cohort!$B:$B,"Meta",Cohort!$A:$A,IF($F$2="All","*",$F$2)),"") | J5: =IFERROR(SUMIFS(Cohort!$F:$F,Cohort!$B:$B,"Meta",Cohort!$A:$A,IF($F$2="All","*",$F$2))/SUMIFS(Cohort!$C:$C,Cohort!$B:$B,"Meta",Cohort!$A:$A,IF($F$2="All","*",$F$2)),"") | K5: =IFERROR(SUMIFS(Cohort!$G:$G,Cohort!$B:$B,"Meta",Cohort!$A:$A,IF($F$2="All","*",$F$2))/SUMIFS(Cohort!$C:$C,Cohort!$B:$B,"Meta",Cohort!$A:$A,IF($F$2="All","*",$F$2)),"") | L5: =IFERROR(SUMIFS(Cohort!$I:$I,Cohort!$B:$B,"Meta",Cohort!$A:$A,IF($F$2="All","*",$F$2))/SUMIFS(Cohort!$C:$C,Cohort!$B:$B,"Meta",Cohort!$A:$A,IF($F$2="All","*",$F$2)),"") | M5: =IFERROR(H5/D5,"") | N5: =H5-D5
A6: OnlyFinder | B6: =SUMIFS(Data!$D:$D,Data!$A:$A,">="&$B$2,Data!$A:$A,"<="&$D$2,Data!$C:$C,"OnlyFinder",Data!$B:$B,IF($F$2="All","*",$F$2)) | C6: =SUMIFS(Data!$E:$E,Data!$A:$A,">="&$B$2,Data!$A:$A,"<="&$D$2,Data!$C:$C,"OnlyFinder",Data!$B:$B,IF($F$2="All","*",$F$2)) | D6: =B6*F6 | E6: =IFERROR(D6/C6,"") | F6: 0.75 | G6: =IFERROR(C6/B6,"") | H6: =SUMIFS(Data!$G:$G,Data!$A:$A,">="&$B$2,Data!$A:$A,"<="&$D$2,Data!$C:$C,"OnlyFinder",Data!$B:$B,IF($F$2="All","*",$F$2)) | I6: =IFERROR(SUMIFS(Cohort!$E:$E,Cohort!$B:$B,"OnlyFinder",Cohort!$A:$A,IF($F$2="All","*",$F$2))/SUMIFS(Cohort!$C:$C,Cohort!$B:$B,"OnlyFinder",Cohort!$A:$A,IF($F$2="All","*",$F$2)),"") | J6: =IFERROR(SUMIFS(Cohort!$F:$F,Cohort!$B:$B,"OnlyFinder",Cohort!$A:$A,IF($F$2="All","*",$F$2))/SUMIFS(Cohort!$C:$C,Cohort!$B:$B,"OnlyFinder",Cohort!$A:$A,IF($F$2="All","*",$F$2)),"") | K6: =IFERROR(SUMIFS(Cohort!$G:$G,Cohort!$B:$B,"OnlyFinder",Cohort!$A:$A,IF($F$2="All","*",$F$2))/SUMIFS(Cohort!$C:$C,Cohort!$B:$B,"OnlyFinder",Cohort!$A:$A,IF($F$2="All","*",$F$2)),"") | L6: =IFERROR(SUMIFS(Cohort!$I:$I,Cohort!$B:$B,"OnlyFinder",Cohort!$A:$A,IF($F$2="All","*",$F$2))/SUMIFS(Cohort!$C:$C,Cohort!$B:$B,"OnlyFinder",Cohort!$A:$A,IF($F$2="All","*",$F$2)),"") | M6: =IFERROR(H6/D6,"") | N6: =H6-D6
A7: OnlyGuider | B7: =SUMIFS(Data!$D:$D,Data!$A:$A,">="&$B$2,Data!$A:$A,"<="&$D$2,Data!$C:$C,"OnlyGuider",Data!$B:$B,IF($F$2="All","*",$F$2)) | C7: =SUMIFS(Data!$E:$E,Data!$A:$A,">="&$B$2,Data!$A:$A,"<="&$D$2,Data!$C:$C,"OnlyGuider",Data!$B:$B,IF($F$2="All","*",$F$2)) | D7: =B7*F7 | E7: =IFERROR(D7/C7,"") | F7: 0.75 | G7: =IFERROR(C7/B7,"") | H7: =SUMIFS(Data!$G:$G,Data!$A:$A,">="&$B$2,Data!$A:$A,"<="&$D$2,Data!$C:$C,"OnlyGuider",Data!$B:$B,IF($F$2="All","*",$F$2)) | I7: =IFERROR(SUMIFS(Cohort!$E:$E,Cohort!$B:$B,"OnlyGuider",Cohort!$A:$A,IF($F$2="All","*",$F$2))/SUMIFS(Cohort!$C:$C,Cohort!$B:$B,"OnlyGuider",Cohort!$A:$A,IF($F$2="All","*",$F$2)),"") | J7: =IFERROR(SUMIFS(Cohort!$F:$F,Cohort!$B:$B,"OnlyGuider",Cohort!$A:$A,IF($F$2="All","*",$F$2))/SUMIFS(Cohort!$C:$C,Cohort!$B:$B,"OnlyGuider",Cohort!$A:$A,IF($F$2="All","*",$F$2)),"") | K7: =IFERROR(SUMIFS(Cohort!$G:$G,Cohort!$B:$B,"OnlyGuider",Cohort!$A:$A,IF($F$2="All","*",$F$2))/SUMIFS(Cohort!$C:$C,Cohort!$B:$B,"OnlyGuider",Cohort!$A:$A,IF($F$2="All","*",$F$2)),"") | L7: =IFERROR(SUMIFS(Cohort!$I:$I,Cohort!$B:$B,"OnlyGuider",Cohort!$A:$A,IF($F$2="All","*",$F$2))/SUMIFS(Cohort!$C:$C,Cohort!$B:$B,"OnlyGuider",Cohort!$A:$A,IF($F$2="All","*",$F$2)),"") | M7: =IFERROR(H7/D7,"") | N7: =H7-D7
A8: OnlySeeker | B8: =SUMIFS(Data!$D:$D,Data!$A:$A,">="&$B$2,Data!$A:$A,"<="&$D$2,Data!$C:$C,"OnlySeeker",Data!$B:$B,IF($F$2="All","*",$F$2)) | C8: =SUMIFS(Data!$E:$E,Data!$A:$A,">="&$B$2,Data!$A:$A,"<="&$D$2,Data!$C:$C,"OnlySeeker",Data!$B:$B,IF($F$2="All","*",$F$2)) | D8: =B8*F8 | E8: =IFERROR(D8/C8,"") | F8: 0.75 | G8: =IFERROR(C8/B8,"") | H8: =SUMIFS(Data!$G:$G,Data!$A:$A,">="&$B$2,Data!$A:$A,"<="&$D$2,Data!$C:$C,"OnlySeeker",Data!$B:$B,IF($F$2="All","*",$F$2)) | I8: =IFERROR(SUMIFS(Cohort!$E:$E,Cohort!$B:$B,"OnlySeeker",Cohort!$A:$A,IF($F$2="All","*",$F$2))/SUMIFS(Cohort!$C:$C,Cohort!$B:$B,"OnlySeeker",Cohort!$A:$A,IF($F$2="All","*",$F$2)),"") | J8: =IFERROR(SUMIFS(Cohort!$F:$F,Cohort!$B:$B,"OnlySeeker",Cohort!$A:$A,IF($F$2="All","*",$F$2))/SUMIFS(Cohort!$C:$C,Cohort!$B:$B,"OnlySeeker",Cohort!$A:$A,IF($F$2="All","*",$F$2)),"") | K8: =IFERROR(SUMIFS(Cohort!$G:$G,Cohort!$B:$B,"OnlySeeker",Cohort!$A:$A,IF($F$2="All","*",$F$2))/SUMIFS(Cohort!$C:$C,Cohort!$B:$B,"OnlySeeker",Cohort!$A:$A,IF($F$2="All","*",$F$2)),"") | L8: =IFERROR(SUMIFS(Cohort!$I:$I,Cohort!$B:$B,"OnlySeeker",Cohort!$A:$A,IF($F$2="All","*",$F$2))/SUMIFS(Cohort!$C:$C,Cohort!$B:$B,"OnlySeeker",Cohort!$A:$A,IF($F$2="All","*",$F$2)),"") | M8: =IFERROR(H8/D8,"") | N8: =H8-D8
A9: OnlyTraffic | B9: =SUMIFS(Data!$D:$D,Data!$A:$A,">="&$B$2,Data!$A:$A,"<="&$D$2,Data!$C:$C,"OnlyTraffic",Data!$B:$B,IF($F$2="All","*",$F$2)) | C9: =SUMIFS(Data!$E:$E,Data!$A:$A,">="&$B$2,Data!$A:$A,"<="&$D$2,Data!$C:$C,"OnlyTraffic",Data!$B:$B,IF($F$2="All","*",$F$2)) | D9: =B9*F9 | E9: =IFERROR(D9/C9,"") | F9: 0.75 | G9: =IFERROR(C9/B9,"") | H9: =SUMIFS(Data!$G:$G,Data!$A:$A,">="&$B$2,Data!$A:$A,"<="&$D$2,Data!$C:$C,"OnlyTraffic",Data!$B:$B,IF($F$2="All","*",$F$2)) | I9: =IFERROR(SUMIFS(Cohort!$E:$E,Cohort!$B:$B,"OnlyTraffic",Cohort!$A:$A,IF($F$2="All","*",$F$2))/SUMIFS(Cohort!$C:$C,Cohort!$B:$B,"OnlyTraffic",Cohort!$A:$A,IF($F$2="All","*",$F$2)),"") | J9: =IFERROR(SUMIFS(Cohort!$F:$F,Cohort!$B:$B,"OnlyTraffic",Cohort!$A:$A,IF($F$2="All","*",$F$2))/SUMIFS(Cohort!$C:$C,Cohort!$B:$B,"OnlyTraffic",Cohort!$A:$A,IF($F$2="All","*",$F$2)),"") | K9: =IFERROR(SUMIFS(Cohort!$G:$G,Cohort!$B:$B,"OnlyTraffic",Cohort!$A:$A,IF($F$2="All","*",$F$2))/SUMIFS(Cohort!$C:$C,Cohort!$B:$B,"OnlyTraffic",Cohort!$A:$A,IF($F$2="All","*",$F$2)),"") | L9: =IFERROR(SUMIFS(Cohort!$I:$I,Cohort!$B:$B,"OnlyTraffic",Cohort!$A:$A,IF($F$2="All","*",$F$2))/SUMIFS(Cohort!$C:$C,Cohort!$B:$B,"OnlyTraffic",Cohort!$A:$A,IF($F$2="All","*",$F$2)),"") | M9: =IFERROR(H9/D9,"") | N9: =H9-D9
A10: TOTAL | B10: =SUMIFS(Data!$D:$D,Data!$A:$A,">="&$B$2,Data!$A:$A,"<="&$D$2,Data!$B:$B,IF($F$2="All","*",$F$2)) | C10: =SUMIFS(Data!$E:$E,Data!$A:$A,">="&$B$2,Data!$A:$A,"<="&$D$2,Data!$B:$B,IF($F$2="All","*",$F$2)) | D10: =SUM(D5:D9) | E10: =IFERROR(D10/C10,"") | F10: =IFERROR(D10/B10,"") | G10: =IFERROR(C10/B10,"") | H10: =SUMIFS(Data!$G:$G,Data!$A:$A,">="&$B$2,Data!$A:$A,"<="&$D$2,Data!$B:$B,IF($F$2="All","*",$F$2)) | I10: =IFERROR(SUMIFS(Cohort!$E:$E,Cohort!$A:$A,IF($F$2="All","*",$F$2))/SUMIFS(Cohort!$C:$C,Cohort!$A:$A,IF($F$2="All","*",$F$2)),"") | J10: =IFERROR(SUMIFS(Cohort!$F:$F,Cohort!$A:$A,IF($F$2="All","*",$F$2))/SUMIFS(Cohort!$C:$C,Cohort!$A:$A,IF($F$2="All","*",$F$2)),"") | K10: =IFERROR(SUMIFS(Cohort!$G:$G,Cohort!$A:$A,IF($F$2="All","*",$F$2))/SUMIFS(Cohort!$C:$C,Cohort!$A:$A,IF($F$2="All","*",$F$2)),"") | L10: =IFERROR(SUMIFS(Cohort!$I:$I,Cohort!$A:$A,IF($F$2="All","*",$F$2))/SUMIFS(Cohort!$C:$C,Cohort!$A:$A,IF($F$2="All","*",$F$2)),"") | M10: =IFERROR(H10/D10,"") | N10: =H10-D10
A12: DAY BY DAY (this week + the next 7 days, by platform — for the chosen creator. Type the Relevance score in yourself.)
A13: Day / Platform | B13: Clicks | C13: Fans | D13: Spend | E13: Cost Per Fan | F13: CPC | G13: CVR | H13: Attributed Revenue | I13: Total Link LTV | J13: ROAS | K13: Agency Profit | L13: Relevance
A14: =$B$2+0 | B14: =SUMIFS(Data!$D:$D,Data!$A:$A,$A14,Data!$B:$B,IF($F$2="All","*",$F$2)) | C14: =SUMIFS(Data!$E:$E,Data!$A:$A,$A14,Data!$B:$B,IF($F$2="All","*",$F$2)) | D14: =SUMIFS(Data!$F:$F,Data!$A:$A,$A14,Data!$B:$B,IF($F$2="All","*",$F$2)) | E14: =IFERROR(D14/C14,"") | F14: =IFERROR(D14/B14,"") | G14: =IFERROR(C14/B14,"") | H14: =SUMIFS(Data!$G:$G,Data!$A:$A,$A14,Data!$B:$B,IF($F$2="All","*",$F$2)) | I14: =IFERROR(H14/C14,"") | J14: =IFERROR(H14/D14,"") | K14: =H14-D14
A15: Meta | B15: =SUMIFS(Data!$D:$D,Data!$A:$A,$A14,Data!$C:$C,"Meta",Data!$B:$B,IF($F$2="All","*",$F$2)) | C15: =SUMIFS(Data!$E:$E,Data!$A:$A,$A14,Data!$C:$C,"Meta",Data!$B:$B,IF($F$2="All","*",$F$2)) | D15: =SUMIFS(Data!$F:$F,Data!$A:$A,$A14,Data!$C:$C,"Meta",Data!$B:$B,IF($F$2="All","*",$F$2)) | E15: =IFERROR(D15/C15,"") | F15: =IFERROR(D15/B15,"") | G15: =IFERROR(C15/B15,"") | H15: =SUMIFS(Data!$G:$G,Data!$A:$A,$A14,Data!$C:$C,"Meta",Data!$B:$B,IF($F$2="All","*",$F$2)) | I15: =IFERROR(H15/C15,"") | J15: =IFERROR(H15/D15,"") | K15: =H15-D15
A16: OnlyFinder | B16: =SUMIFS(Data!$D:$D,Data!$A:$A,$A14,Data!$C:$C,"OnlyFinder",Data!$B:$B,IF($F$2="All","*",$F$2)) | C16: =SUMIFS(Data!$E:$E,Data!$A:$A,$A14,Data!$C:$C,"OnlyFinder",Data!$B:$B,IF($F$2="All","*",$F$2)) | D16: =SUMIFS(Data!$F:$F,Data!$A:$A,$A14,Data!$C:$C,"OnlyFinder",Data!$B:$B,IF($F$2="All","*",$F$2)) | E16: =IFERROR(D16/C16,"") | F16: =IFERROR(D16/B16,"") | G16: =IFERROR(C16/B16,"") | H16: =SUMIFS(Data!$G:$G,Data!$A:$A,$A14,Data!$C:$C,"OnlyFinder",Data!$B:$B,IF($F$2="All","*",$F$2)) | I16: =IFERROR(H16/C16,"") | J16: =IFERROR(H16/D16,"") | K16: =H16-D16
A17: OnlyGuider | B17: =SUMIFS(Data!$D:$D,Data!$A:$A,$A14,Data!$C:$C,"OnlyGuider",Data!$B:$B,IF($F$2="All","*",$F$2)) | C17: =SUMIFS(Data!$E:$E,Data!$A:$A,$A14,Data!$C:$C,"OnlyGuider",Data!$B:$B,IF($F$2="All","*",$F$2)) | D17: =SUMIFS(Data!$F:$F,Data!$A:$A,$A14,Data!$C:$C,"OnlyGuider",Data!$B:$B,IF($F$2="All","*",$F$2)) | E17: =IFERROR(D17/C17,"") | F17: =IFERROR(D17/B17,"") | G17: =IFERROR(C17/B17,"") | H17: =SUMIFS(Data!$G:$G,Data!$A:$A,$A14,Data!$C:$C,"OnlyGuider",Data!$B:$B,IF($F$2="All","*",$F$2)) | I17: =IFERROR(H17/C17,"") | J17: =IFERROR(H17/D17,"") | K17: =H17-D17
A18: OnlySeeker | B18: =SUMIFS(Data!$D:$D,Data!$A:$A,$A14,Data!$C:$C,"OnlySeeker",Data!$B:$B,IF($F$2="All","*",$F$2)) | C18: =SUMIFS(Data!$E:$E,Data!$A:$A,$A14,Data!$C:$C,"OnlySeeker",Data!$B:$B,IF($F$2="All","*",$F$2)) | D18: =SUMIFS(Data!$F:$F,Data!$A:$A,$A14,Data!$C:$C,"OnlySeeker",Data!$B:$B,IF($F$2="All","*",$F$2)) | E18: =IFERROR(D18/C18,"") | F18: =IFERROR(D18/B18,"") | G18: =IFERROR(C18/B18,"") | H18: =SUMIFS(Data!$G:$G,Data!$A:$A,$A14,Data!$C:$C,"OnlySeeker",Data!$B:$B,IF($F$2="All","*",$F$2)) | I18: =IFERROR(H18/C18,"") | J18: =IFERROR(H18/D18,"") | K18: =H18-D18
A19: OnlyTraffic | B19: =SUMIFS(Data!$D:$D,Data!$A:$A,$A14,Data!$C:$C,"OnlyTraffic",Data!$B:$B,IF($F$2="All","*",$F$2)) | C19: =SUMIFS(Data!$E:$E,Data!$A:$A,$A14,Data!$C:$C,"OnlyTraffic",Data!$B:$B,IF($F$2="All","*",$F$2)) | D19: =SUMIFS(Data!$F:$F,Data!$A:$A,$A14,Data!$C:$C,"OnlyTraffic",Data!$B:$B,IF($F$2="All","*",$F$2)) | E19: =IFERROR(D19/C19,"") | F19: =IFERROR(D19/B19,"") | G19: =IFERROR(C19/B19,"") | H19: =SUMIFS(Data!$G:$G,Data!$A:$A,$A14,Data!$C:$C,"OnlyTraffic",Data!$B:$B,IF($F$2="All","*",$F$2)) | I19: =IFERROR(H19/C19,"") | J19: =IFERROR(H19/D19,"") | K19: =H19-D19
A20: =$B$2+1 | B20: =SUMIFS(Data!$D:$D,Data!$A:$A,$A20,Data!$B:$B,IF($F$2="All","*",$F$2)) | C20: =SUMIFS(Data!$E:$E,Data!$A:$A,$A20,Data!$B:$B,IF($F$2="All","*",$F$2)) | D20: =SUMIFS(Data!$F:$F,Data!$A:$A,$A20,Data!$B:$B,IF($F$2="All","*",$F$2)) | E20: =IFERROR(D20/C20,"") | F20: =IFERROR(D20/B20,"") | G20: =IFERROR(C20/B20,"") | H20: =SUMIFS(Data!$G:$G,Data!$A:$A,$A20,Data!$B:$B,IF($F$2="All","*",$F$2)) | I20: =IFERROR(H20/C20,"") | J20: =IFERROR(H20/D20,"") | K20: =H20-D20
A21: Meta | B21: =SUMIFS(Data!$D:$D,Data!$A:$A,$A20,Data!$C:$C,"Meta",Data!$B:$B,IF($F$2="All","*",$F$2)) | C21: =SUMIFS(Data!$E:$E,Data!$A:$A,$A20,Data!$C:$C,"Meta",Data!$B:$B,IF($F$2="All","*",$F$2)) | D21: =SUMIFS(Data!$F:$F,Data!$A:$A,$A20,Data!$C:$C,"Meta",Data!$B:$B,IF($F$2="All","*",$F$2)) | E21: =IFERROR(D21/C21,"") | F21: =IFERROR(D21/B21,"") | G21: =IFERROR(C21/B21,"") | H21: =SUMIFS(Data!$G:$G,Data!$A:$A,$A20,Data!$C:$C,"Meta",Data!$B:$B,IF($F$2="All","*",$F$2)) | I21: =IFERROR(H21/C21,"") | J21: =IFERROR(H21/D21,"") | K21: =H21-D21
A22: OnlyFinder | B22: =SUMIFS(Data!$D:$D,Data!$A:$A,$A20,Data!$C:$C,"OnlyFinder",Data!$B:$B,IF($F$2="All","*",$F$2)) | C22: =SUMIFS(Data!$E:$E,Data!$A:$A,$A20,Data!$C:$C,"OnlyFinder",Data!$B:$B,IF($F$2="All","*",$F$2)) | D22: =SUMIFS(Data!$F:$F,Data!$A:$A,$A20,Data!$C:$C,"OnlyFinder",Data!$B:$B,IF($F$2="All","*",$F$2)) | E22: =IFERROR(D22/C22,"") | F22: =IFERROR(D22/B22,"") | G22: =IFERROR(C22/B22,"") | H22: =SUMIFS(Data!$G:$G,Data!$A:$A,$A20,Data!$C:$C,"OnlyFinder",Data!$B:$B,IF($F$2="All","*",$F$2)) | I22: =IFERROR(H22/C22,"") | J22: =IFERROR(H22/D22,"") | K22: =H22-D22
A23: OnlyGuider | B23: =SUMIFS(Data!$D:$D,Data!$A:$A,$A20,Data!$C:$C,"OnlyGuider",Data!$B:$B,IF($F$2="All","*",$F$2)) | C23: =SUMIFS(Data!$E:$E,Data!$A:$A,$A20,Data!$C:$C,"OnlyGuider",Data!$B:$B,IF($F$2="All","*",$F$2)) | D23: =SUMIFS(Data!$F:$F,Data!$A:$A,$A20,Data!$C:$C,"OnlyGuider",Data!$B:$B,IF($F$2="All","*",$F$2)) | E23: =IFERROR(D23/C23,"") | F23: =IFERROR(D23/B23,"") | G23: =IFERROR(C23/B23,"") | H23: =SUMIFS(Data!$G:$G,Data!$A:$A,$A20,Data!$C:$C,"OnlyGuider",Data!$B:$B,IF($F$2="All","*",$F$2)) | I23: =IFERROR(H23/C23,"") | J23: =IFERROR(H23/D23,"") | K23: =H23-D23
A24: OnlySeeker | B24: =SUMIFS(Data!$D:$D,Data!$A:$A,$A20,Data!$C:$C,"OnlySeeker",Data!$B:$B,IF($F$2="All","*",$F$2)) | C24: =SUMIFS(Data!$E:$E,Data!$A:$A,$A20,Data!$C:$C,"OnlySeeker",Data!$B:$B,IF($F$2="All","*",$F$2)) | D24: =SUMIFS(Data!$F:$F,Data!$A:$A,$A20,Data!$C:$C,"OnlySeeker",Data!$B:$B,IF($F$2="All","*",$F$2)) | E24: =IFERROR(D24/C24,"") | F24: =IFERROR(D24/B24,"") | G24: =IFERROR(C24/B24,"") | H24: =SUMIFS(Data!$G:$G,Data!$A:$A,$A20,Data!$C:$C,"OnlySeeker",Data!$B:$B,IF($F$2="All","*",$F$2)) | I24: =IFERROR(H24/C24,"") | J24: =IFERROR(H24/D24,"") | K24: =H24-D24
A25: OnlyTraffic | B25: =SUMIFS(Data!$D:$D,Data!$A:$A,$A20,Data!$C:$C,"OnlyTraffic",Data!$B:$B,IF($F$2="All","*",$F$2)) | C25: =SUMIFS(Data!$E:$E,Data!$A:$A,$A20,Data!$C:$C,"OnlyTraffic",Data!$B:$B,IF($F$2="All","*",$F$2)) | D25: =SUMIFS(Data!$F:$F,Data!$A:$A,$A20,Data!$C:$C,"OnlyTraffic",Data!$B:$B,IF($F$2="All","*",$F$2)) | E25: =IFERROR(D25/C25,"") | F25: =IFERROR(D25/B25,"") | G25: =IFERROR(C25/B25,"") | H25: =SUMIFS(Data!$G:$G,Data!$A:$A,$A20,Data!$C:$C,"OnlyTraffic",Data!$B:$B,IF($F$2="All","*",$F$2)) | I25: =IFERROR(H25/C25,"") | J25: =IFERROR(H25/D25,"") | K25: =H25-D25
A26: =$B$2+2 | B26: =SUMIFS(Data!$D:$D,Data!$A:$A,$A26,Data!$B:$B,IF($F$2="All","*",$F$2)) | C26: =SUMIFS(Data!$E:$E,Data!$A:$A,$A26,Data!$B:$B,IF($F$2="All","*",$F$2)) | D26: =SUMIFS(Data!$F:$F,Data!$A:$A,$A26,Data!$B:$B,IF($F$2="All","*",$F$2)) | E26: =IFERROR(D26/C26,"") | F26: =IFERROR(D26/B26,"") | G26: =IFERROR(C26/B26,"") | H26: =SUMIFS(Data!$G:$G,Data!$A:$A,$A26,Data!$B:$B,IF($F$2="All","*",$F$2)) | I26: =IFERROR(H26/C26,"") | J26: =IFERROR(H26/D26,"") | K26: =H26-D26
A27: Meta | B27: =SUMIFS(Data!$D:$D,Data!$A:$A,$A26,Data!$C:$C,"Meta",Data!$B:$B,IF($F$2="All","*",$F$2)) | C27: =SUMIFS(Data!$E:$E,Data!$A:$A,$A26,Data!$C:$C,"Meta",Data!$B:$B,IF($F$2="All","*",$F$2)) | D27: =SUMIFS(Data!$F:$F,Data!$A:$A,$A26,Data!$C:$C,"Meta",Data!$B:$B,IF($F$2="All","*",$F$2)) | E27: =IFERROR(D27/C27,"") | F27: =IFERROR(D27/B27,"") | G27: =IFERROR(C27/B27,"") | H27: =SUMIFS(Data!$G:$G,Data!$A:$A,$A26,Data!$C:$C,"Meta",Data!$B:$B,IF($F$2="All","*",$F$2)) | I27: =IFERROR(H27/C27,"") | J27: =IFERROR(H27/D27,"") | K27: =H27-D27
A28: OnlyFinder | B28: =SUMIFS(Data!$D:$D,Data!$A:$A,$A26,Data!$C:$C,"OnlyFinder",Data!$B:$B,IF($F$2="All","*",$F$2)) | C28: =SUMIFS(Data!$E:$E,Data!$A:$A,$A26,Data!$C:$C,"OnlyFinder",Data!$B:$B,IF($F$2="All","*",$F$2)) | D28: =SUMIFS(Data!$F:$F,Data!$A:$A,$A26,Data!$C:$C,"OnlyFinder",Data!$B:$B,IF($F$2="All","*",$F$2)) | E28: =IFERROR(D28/C28,"") | F28: =IFERROR(D28/B28,"") | G28: =IFERROR(C28/B28,"") | H28: =SUMIFS(Data!$G:$G,Data!$A:$A,$A26,Data!$C:$C,"OnlyFinder",Data!$B:$B,IF($F$2="All","*",$F$2)) | I28: =IFERROR(H28/C28,"") | J28: =IFERROR(H28/D28,"") | K28: =H28-D28
A29: OnlyGuider | B29: =SUMIFS(Data!$D:$D,Data!$A:$A,$A26,Data!$C:$C,"OnlyGuider",Data!$B:$B,IF($F$2="All","*",$F$2)) | C29: =SUMIFS(Data!$E:$E,Data!$A:$A,$A26,Data!$C:$C,"OnlyGuider",Data!$B:$B,IF($F$2="All","*",$F$2)) | D29: =SUMIFS(Data!$F:$F,Data!$A:$A,$A26,Data!$C:$C,"OnlyGuider",Data!$B:$B,IF($F$2="All","*",$F$2)) | E29: =IFERROR(D29/C29,"") | F29: =IFERROR(D29/B29,"") | G29: =IFERROR(C29/B29,"") | H29: =SUMIFS(Data!$G:$G,Data!$A:$A,$A26,Data!$C:$C,"OnlyGuider",Data!$B:$B,IF($F$2="All","*",$F$2)) | I29: =IFERROR(H29/C29,"") | J29: =IFERROR(H29/D29,"") | K29: =H29-D29
A30: OnlySeeker | B30: =SUMIFS(Data!$D:$D,Data!$A:$A,$A26,Data!$C:$C,"OnlySeeker",Data!$B:$B,IF($F$2="All","*",$F$2)) | C30: =SUMIFS(Data!$E:$E,Data!$A:$A,$A26,Data!$C:$C,"OnlySeeker",Data!$B:$B,IF($F$2="All","*",$F$2)) | D30: =SUMIFS(Data!$F:$F,Data!$A:$A,$A26,Data!$C:$C,"OnlySeeker",Data!$B:$B,IF($F$2="All","*",$F$2)) | E30: =IFERROR(D30/C30,"") | F30: =IFERROR(D30/B30,"") | G30: =IFERROR(C30/B30,"") | H30: =SUMIFS(Data!$G:$G,Data!$A:$A,$A26,Data!$C:$C,"OnlySeeker",Data!$B:$B,IF($F$2="All","*",$F$2)) | I30: =IFERROR(H30/C30,"") | J30: =IFERROR(H30/D30,"") | K30: =H30-D30
A31: OnlyTraffic | B31: =SUMIFS(Data!$D:$D,Data!$A:$A,$A26,Data!$C:$C,"OnlyTraffic",Data!$B:$B,IF($F$2="All","*",$F$2)) | C31: =SUMIFS(Data!$E:$E,Data!$A:$A,$A26,Data!$C:$C,"OnlyTraffic",Data!$B:$B,IF($F$2="All","*",$F$2)) | D31: =SUMIFS(Data!$F:$F,Data!$A:$A,$A26,Data!$C:$C,"OnlyTraffic",Data!$B:$B,IF($F$2="All","*",$F$2)) | E31: =IFERROR(D31/C31,"") | F31: =IFERROR(D31/B31,"") | G31: =IFERROR(C31/B31,"") | H31: =SUMIFS(Data!$G:$G,Data!$A:$A,$A26,Data!$C:$C,"OnlyTraffic",Data!$B:$B,IF($F$2="All","*",$F$2)) | I31: =IFERROR(H31/C31,"") | J31: =IFERROR(H31/D31,"") | K31: =H31-D31
A32: =$B$2+3 | B32: =SUMIFS(Data!$D:$D,Data!$A:$A,$A32,Data!$B:$B,IF($F$2="All","*",$F$2)) | C32: =SUMIFS(Data!$E:$E,Data!$A:$A,$A32,Data!$B:$B,IF($F$2="All","*",$F$2)) | D32: =SUMIFS(Data!$F:$F,Data!$A:$A,$A32,Data!$B:$B,IF($F$2="All","*",$F$2)) | E32: =IFERROR(D32/C32,"") | F32: =IFERROR(D32/B32,"") | G32: =IFERROR(C32/B32,"") | H32: =SUMIFS(Data!$G:$G,Data!$A:$A,$A32,Data!$B:$B,IF($F$2="All","*",$F$2)) | I32: =IFERROR(H32/C32,"") | J32: =IFERROR(H32/D32,"") | K32: =H32-D32
A33: Meta | B33: =SUMIFS(Data!$D:$D,Data!$A:$A,$A32,Data!$C:$C,"Meta",Data!$B:$B,IF($F$2="All","*",$F$2)) | C33: =SUMIFS(Data!$E:$E,Data!$A:$A,$A32,Data!$C:$C,"Meta",Data!$B:$B,IF($F$2="All","*",$F$2)) | D33: =SUMIFS(Data!$F:$F,Data!$A:$A,$A32,Data!$C:$C,"Meta",Data!$B:$B,IF($F$2="All","*",$F$2)) | E33: =IFERROR(D33/C33,"") | F33: =IFERROR(D33/B33,"") | G33: =IFERROR(C33/B33,"") | H33: =SUMIFS(Data!$G:$G,Data!$A:$A,$A32,Data!$C:$C,"Meta",Data!$B:$B,IF($F$2="All","*",$F$2)) | I33: =IFERROR(H33/C33,"") | J33: =IFERROR(H33/D33,"") | K33: =H33-D33
A34: OnlyFinder | B34: =SUMIFS(Data!$D:$D,Data!$A:$A,$A32,Data!$C:$C,"OnlyFinder",Data!$B:$B,IF($F$2="All","*",$F$2)) | C34: =SUMIFS(Data!$E:$E,Data!$A:$A,$A32,Data!$C:$C,"OnlyFinder",Data!$B:$B,IF($F$2="All","*",$F$2)) | D34: =SUMIFS(Data!$F:$F,Data!$A:$A,$A32,Data!$C:$C,"OnlyFinder",Data!$B:$B,IF($F$2="All","*",$F$2)) | E34: =IFERROR(D34/C34,"") | F34: =IFERROR(D34/B34,"") | G34: =IFERROR(C34/B34,"") | H34: =SUMIFS(Data!$G:$G,Data!$A:$A,$A32,Data!$C:$C,"OnlyFinder",Data!$B:$B,IF($F$2="All","*",$F$2)) | I34: =IFERROR(H34/C34,"") | J34: =IFERROR(H34/D34,"") | K34: =H34-D34
A35: OnlyGuider | B35: =SUMIFS(Data!$D:$D,Data!$A:$A,$A32,Data!$C:$C,"OnlyGuider",Data!$B:$B,IF($F$2="All","*",$F$2)) | C35: =SUMIFS(Data!$E:$E,Data!$A:$A,$A32,Data!$C:$C,"OnlyGuider",Data!$B:$B,IF($F$2="All","*",$F$2)) | D35: =SUMIFS(Data!$F:$F,Data!$A:$A,$A32,Data!$C:$C,"OnlyGuider",Data!$B:$B,IF($F$2="All","*",$F$2)) | E35: =IFERROR(D35/C35,"") | F35: =IFERROR(D35/B35,"") | G35: =IFERROR(C35/B35,"") | H35: =SUMIFS(Data!$G:$G,Data!$A:$A,$A32,Data!$C:$C,"OnlyGuider",Data!$B:$B,IF($F$2="All","*",$F$2)) | I35: =IFERROR(H35/C35,"") | J35: =IFERROR(H35/D35,"") | K35: =H35-D35
A36: OnlySeeker | B36: =SUMIFS(Data!$D:$D,Data!$A:$A,$A32,Data!$C:$C,"OnlySeeker",Data!$B:$B,IF($F$2="All","*",$F$2)) | C36: =SUMIFS(Data!$E:$E,Data!$A:$A,$A32,Data!$C:$C,"OnlySeeker",Data!$B:$B,IF($F$2="All","*",$F$2)) | D36: =SUMIFS(Data!$F:$F,Data!$A:$A,$A32,Data!$C:$C,"OnlySeeker",Data!$B:$B,IF($F$2="All","*",$F$2)) | E36: =IFERROR(D36/C36,"") | F36: =IFERROR(D36/B36,"") | G36: =IFERROR(C36/B36,"") | H36: =SUMIFS(Data!$G:$G,Data!$A:$A,$A32,Data!$C:$C,"OnlySeeker",Data!$B:$B,IF($F$2="All","*",$F$2)) | I36: =IFERROR(H36/C36,"") | J36: =IFERROR(H36/D36,"") | K36: =H36-D36
A37: OnlyTraffic | B37: =SUMIFS(Data!$D:$D,Data!$A:$A,$A32,Data!$C:$C,"OnlyTraffic",Data!$B:$B,IF($F$2="All","*",$F$2)) | C37: =SUMIFS(Data!$E:$E,Data!$A:$A,$A32,Data!$C:$C,"OnlyTraffic",Data!$B:$B,IF($F$2="All","*",$F$2)) | D37: =SUMIFS(Data!$F:$F,Data!$A:$A,$A32,Data!$C:$C,"OnlyTraffic",Data!$B:$B,IF($F$2="All","*",$F$2)) | E37: =IFERROR(D37/C37,"") | F37: =IFERROR(D37/B37,"") | G37: =IFERROR(C37/B37,"") | H37: =SUMIFS(Data!$G:$G,Data!$A:$A,$A32,Data!$C:$C,"OnlyTraffic",Data!$B:$B,IF($F$2="All","*",$F$2)) | I37: =IFERROR(H37/C37,"") | J37: =IFERROR(H37/D37,"") | K37: =H37-D37
A38: =$B$2+4 | B38: =SUMIFS(Data!$D:$D,Data!$A:$A,$A38,Data!$B:$B,IF($F$2="All","*",$F$2)) | C38: =SUMIFS(Data!$E:$E,Data!$A:$A,$A38,Data!$B:$B,IF($F$2="All","*",$F$2)) | D38: =SUMIFS(Data!$F:$F,Data!$A:$A,$A38,Data!$B:$B,IF($F$2="All","*",$F$2)) | E38: =IFERROR(D38/C38,"") | F38: =IFERROR(D38/B38,"") | G38: =IFERROR(C38/B38,"") | H38: =SUMIFS(Data!$G:$G,Data!$A:$A,$A38,Data!$B:$B,IF($F$2="All","*",$F$2)) | I38: =IFERROR(H38/C38,"") | J38: =IFERROR(H38/D38,"") | K38: =H38-D38
A39: Meta | B39: =SUMIFS(Data!$D:$D,Data!$A:$A,$A38,Data!$C:$C,"Meta",Data!$B:$B,IF($F$2="All","*",$F$2)) | C39: =SUMIFS(Data!$E:$E,Data!$A:$A,$A38,Data!$C:$C,"Meta",Data!$B:$B,IF($F$2="All","*",$F$2)) | D39: =SUMIFS(Data!$F:$F,Data!$A:$A,$A38,Data!$C:$C,"Meta",Data!$B:$B,IF($F$2="All","*",$F$2)) | E39: =IFERROR(D39/C39,"") | F39: =IFERROR(D39/B39,"") | G39: =IFERROR(C39/B39,"") | H39: =SUMIFS(Data!$G:$G,Data!$A:$A,$A38,Data!$C:$C,"Meta",Data!$B:$B,IF($F$2="All","*",$F$2)) | I39: =IFERROR(H39/C39,"") | J39: =IFERROR(H39/D39,"") | K39: =H39-D39
A40: OnlyFinder | B40: =SUMIFS(Data!$D:$D,Data!$A:$A,$A38,Data!$C:$C,"OnlyFinder",Data!$B:$B,IF($F$2="All","*",$F$2)) | C40: =SUMIFS(Data!$E:$E,Data!$A:$A,$A38,Data!$C:$C,"OnlyFinder",Data!$B:$B,IF($F$2="All","*",$F$2)) | D40: =SUMIFS(Data!$F:$F,Data!$A:$A,$A38,Data!$C:$C,"OnlyFinder",Data!$B:$B,IF($F$2="All","*",$F$2)) | E40: =IFERROR(D40/C40,"") | F40: =IFERROR(D40/B40,"") | G40: =IFERROR(C40/B40,"") | H40: =SUMIFS(Data!$G:$G,Data!$A:$A,$A38,Data!$C:$C,"OnlyFinder",Data!$B:$B,IF($F$2="All","*",$F$2)) | I40: =IFERROR(H40/C40,"") | J40: =IFERROR(H40/D40,"") | K40: =H40-D40
A41: OnlyGuider | B41: =SUMIFS(Data!$D:$D,Data!$A:$A,$A38,Data!$C:$C,"OnlyGuider",Data!$B:$B,IF($F$2="All","*",$F$2)) | C41: =SUMIFS(Data!$E:$E,Data!$A:$A,$A38,Data!$C:$C,"OnlyGuider",Data!$B:$B,IF($F$2="All","*",$F$2)) | D41: =SUMIFS(Data!$F:$F,Data!$A:$A,$A38,Data!$C:$C,"OnlyGuider",Data!$B:$B,IF($F$2="All","*",$F$2)) | E41: =IFERROR(D41/C41,"") | F41: =IFERROR(D41/B41,"") | G41: =IFERROR(C41/B41,"") | H41: =SUMIFS(Data!$G:$G,Data!$A:$A,$A38,Data!$C:$C,"OnlyGuider",Data!$B:$B,IF($F$2="All","*",$F$2)) | I41: =IFERROR(H41/C41,"") | J41: =IFERROR(H41/D41,"") | K41: =H41-D41
A42: OnlySeeker | B42: =SUMIFS(Data!$D:$D,Data!$A:$A,$A38,Data!$C:$C,"OnlySeeker",Data!$B:$B,IF($F$2="All","*",$F$2)) | C42: =SUMIFS(Data!$E:$E,Data!$A:$A,$A38,Data!$C:$C,"OnlySeeker",Data!$B:$B,IF($F$2="All","*",$F$2)) | D42: =SUMIFS(Data!$F:$F,Data!$A:$A,$A38,Data!$C:$C,"OnlySeeker",Data!$B:$B,IF($F$2="All","*",$F$2)) | E42: =IFERROR(D42/C42,"") | F42: =IFERROR(D42/B42,"") | G42: =IFERROR(C42/B42,"") | H42: =SUMIFS(Data!$G:$G,Data!$A:$A,$A38,Data!$C:$C,"OnlySeeker",Data!$B:$B,IF($F$2="All","*",$F$2)) | I42: =IFERROR(H42/C42,"") | J42: =IFERROR(H42/D42,"") | K42: =H42-D42
A43: OnlyTraffic | B43: =SUMIFS(Data!$D:$D,Data!$A:$A,$A38,Data!$C:$C,"OnlyTraffic",Data!$B:$B,IF($F$2="All","*",$F$2)) | C43: =SUMIFS(Data!$E:$E,Data!$A:$A,$A38,Data!$C:$C,"OnlyTraffic",Data!$B:$B,IF($F$2="All","*",$F$2)) | D43: =SUMIFS(Data!$F:$F,Data!$A:$A,$A38,Data!$C:$C,"OnlyTraffic",Data!$B:$B,IF($F$2="All","*",$F$2)) | E43: =IFERROR(D43/C43,"") | F43: =IFERROR(D43/B43,"") | G43: =IFERROR(C43/B43,"") | H43: =SUMIFS(Data!$G:$G,Data!$A:$A,$A38,Data!$C:$C,"OnlyTraffic",Data!$B:$B,IF($F$2="All","*",$F$2)) | I43: =IFERROR(H43/C43,"") | J43: =IFERROR(H43/D43,"") | K43: =H43-D43
A44: =$B$2+5 | B44: =SUMIFS(Data!$D:$D,Data!$A:$A,$A44,Data!$B:$B,IF($F$2="All","*",$F$2)) | C44: =SUMIFS(Data!$E:$E,Data!$A:$A,$A44,Data!$B:$B,IF($F$2="All","*",$F$2)) | D44: =SUMIFS(Data!$F:$F,Data!$A:$A,$A44,Data!$B:$B,IF($F$2="All","*",$F$2)) | E44: =IFERROR(D44/C44,"") | F44: =IFERROR(D44/B44,"") | G44: =IFERROR(C44/B44,"") | H44: =SUMIFS(Data!$G:$G,Data!$A:$A,$A44,Data!$B:$B,IF($F$2="All","*",$F$2)) | I44: =IFERROR(H44/C44,"") | J44: =IFERROR(H44/D44,"") | K44: =H44-D44
A45: Meta | B45: =SUMIFS(Data!$D:$D,Data!$A:$A,$A44,Data!$C:$C,"Meta",Data!$B:$B,IF($F$2="All","*",$F$2)) | C45: =SUMIFS(Data!$E:$E,Data!$A:$A,$A44,Data!$C:$C,"Meta",Data!$B:$B,IF($F$2="All","*",$F$2)) | D45: =SUMIFS(Data!$F:$F,Data!$A:$A,$A44,Data!$C:$C,"Meta",Data!$B:$B,IF($F$2="All","*",$F$2)) | E45: =IFERROR(D45/C45,"") | F45: =IFERROR(D45/B45,"") | G45: =IFERROR(C45/B45,"") | H45: =SUMIFS(Data!$G:$G,Data!$A:$A,$A44,Data!$C:$C,"Meta",Data!$B:$B,IF($F$2="All","*",$F$2)) | I45: =IFERROR(H45/C45,"") | J45: =IFERROR(H45/D45,"") | K45: =H45-D45
A46: OnlyFinder | B46: =SUMIFS(Data!$D:$D,Data!$A:$A,$A44,Data!$C:$C,"OnlyFinder",Data!$B:$B,IF($F$2="All","*",$F$2)) | C46: =SUMIFS(Data!$E:$E,Data!$A:$A,$A44,Data!$C:$C,"OnlyFinder",Data!$B:$B,IF($F$2="All","*",$F$2)) | D46: =SUMIFS(Data!$F:$F,Data!$A:$A,$A44,Data!$C:$C,"OnlyFinder",Data!$B:$B,IF($F$2="All","*",$F$2)) | E46: =IFERROR(D46/C46,"") | F46: =IFERROR(D46/B46,"") | G46: =IFERROR(C46/B46,"") | H46: =SUMIFS(Data!$G:$G,Data!$A:$A,$A44,Data!$C:$C,"OnlyFinder",Data!$B:$B,IF($F$2="All","*",$F$2)) | I46: =IFERROR(H46/C46,"") | J46: =IFERROR(H46/D46,"") | K46: =H46-D46
A47: OnlyGuider | B47: =SUMIFS(Data!$D:$D,Data!$A:$A,$A44,Data!$C:$C,"OnlyGuider",Data!$B:$B,IF($F$2="All","*",$F$2)) | C47: =SUMIFS(Data!$E:$E,Data!$A:$A,$A44,Data!$C:$C,"OnlyGuider",Data!$B:$B,IF($F$2="All","*",$F$2)) | D47: =SUMIFS(Data!$F:$F,Data!$A:$A,$A44,Data!$C:$C,"OnlyGuider",Data!$B:$B,IF($F$2="All","*",$F$2)) | E47: =IFERROR(D47/C47,"") | F47: =IFERROR(D47/B47,"") | G47: =IFERROR(C47/B47,"") | H47: =SUMIFS(Data!$G:$G,Data!$A:$A,$A44,Data!$C:$C,"OnlyGuider",Data!$B:$B,IF($F$2="All","*",$F$2)) | I47: =IFERROR(H47/C47,"") | J47: =IFERROR(H47/D47,"") | K47: =H47-D47
A48: OnlySeeker | B48: =SUMIFS(Data!$D:$D,Data!$A:$A,$A44,Data!$C:$C,"OnlySeeker",Data!$B:$B,IF($F$2="All","*",$F$2)) | C48: =SUMIFS(Data!$E:$E,Data!$A:$A,$A44,Data!$C:$C,"OnlySeeker",Data!$B:$B,IF($F$2="All","*",$F$2)) | D48: =SUMIFS(Data!$F:$F,Data!$A:$A,$A44,Data!$C:$C,"OnlySeeker",Data!$B:$B,IF($F$2="All","*",$F$2)) | E48: =IFERROR(D48/C48,"") | F48: =IFERROR(D48/B48,"") | G48: =IFERROR(C48/B48,"") | H48: =SUMIFS(Data!$G:$G,Data!$A:$A,$A44,Data!$C:$C,"OnlySeeker",Data!$B:$B,IF($F$2="All","*",$F$2)) | I48: =IFERROR(H48/C48,"") | J48: =IFERROR(H48/D48,"") | K48: =H48-D48
A49: OnlyTraffic | B49: =SUMIFS(Data!$D:$D,Data!$A:$A,$A44,Data!$C:$C,"OnlyTraffic",Data!$B:$B,IF($F$2="All","*",$F$2)) | C49: =SUMIFS(Data!$E:$E,Data!$A:$A,$A44,Data!$C:$C,"OnlyTraffic",Data!$B:$B,IF($F$2="All","*",$F$2)) | D49: =SUMIFS(Data!$F:$F,Data!$A:$A,$A44,Data!$C:$C,"OnlyTraffic",Data!$B:$B,IF($F$2="All","*",$F$2)) | E49: =IFERROR(D49/C49,"") | F49: =IFERROR(D49/B49,"") | G49: =IFERROR(C49/B49,"") | H49: =SUMIFS(Data!$G:$G,Data!$A:$A,$A44,Data!$C:$C,"OnlyTraffic",Data!$B:$B,IF($F$2="All","*",$F$2)) | I49: =IFERROR(H49/C49,"") | J49: =IFERROR(H49/D49,"") | K49: =H49-D49
A50: =$B$2+6 | B50: =SUMIFS(Data!$D:$D,Data!$A:$A,$A50,Data!$B:$B,IF($F$2="All","*",$F$2)) | C50: =SUMIFS(Data!$E:$E,Data!$A:$A,$A50,Data!$B:$B,IF($F$2="All","*",$F$2)) | D50: =SUMIFS(Data!$F:$F,Data!$A:$A,$A50,Data!$B:$B,IF($F$2="All","*",$F$2)) | E50: =IFERROR(D50/C50,"") | F50: =IFERROR(D50/B50,"") | G50: =IFERROR(C50/B50,"") | H50: =SUMIFS(Data!$G:$G,Data!$A:$A,$A50,Data!$B:$B,IF($F$2="All","*",$F$2)) | I50: =IFERROR(H50/C50,"") | J50: =IFERROR(H50/D50,"") | K50: =H50-D50
A51: Meta | B51: =SUMIFS(Data!$D:$D,Data!$A:$A,$A50,Data!$C:$C,"Meta",Data!$B:$B,IF($F$2="All","*",$F$2)) | C51: =SUMIFS(Data!$E:$E,Data!$A:$A,$A50,Data!$C:$C,"Meta",Data!$B:$B,IF($F$2="All","*",$F$2)) | D51: =SUMIFS(Data!$F:$F,Data!$A:$A,$A50,Data!$C:$C,"Meta",Data!$B:$B,IF($F$2="All","*",$F$2)) | E51: =IFERROR(D51/C51,"") | F51: =IFERROR(D51/B51,"") | G51: =IFERROR(C51/B51,"") | H51: =SUMIFS(Data!$G:$G,Data!$A:$A,$A50,Data!$C:$C,"Meta",Data!$B:$B,IF($F$2="All","*",$F$2)) | I51: =IFERROR(H51/C51,"") | J51: =IFERROR(H51/D51,"") | K51: =H51-D51
A52: OnlyFinder | B52: =SUMIFS(Data!$D:$D,Data!$A:$A,$A50,Data!$C:$C,"OnlyFinder",Data!$B:$B,IF($F$2="All","*",$F$2)) | C52: =SUMIFS(Data!$E:$E,Data!$A:$A,$A50,Data!$C:$C,"OnlyFinder",Data!$B:$B,IF($F$2="All","*",$F$2)) | D52: =SUMIFS(Data!$F:$F,Data!$A:$A,$A50,Data!$C:$C,"OnlyFinder",Data!$B:$B,IF($F$2="All","*",$F$2)) | E52: =IFERROR(D52/C52,"") | F52: =IFERROR(D52/B52,"") | G52: =IFERROR(C52/B52,"") | H52: =SUMIFS(Data!$G:$G,Data!$A:$A,$A50,Data!$C:$C,"OnlyFinder",Data!$B:$B,IF($F$2="All","*",$F$2)) | I52: =IFERROR(H52/C52,"") | J52: =IFERROR(H52/D52,"") | K52: =H52-D52
A53: OnlyGuider | B53: =SUMIFS(Data!$D:$D,Data!$A:$A,$A50,Data!$C:$C,"OnlyGuider",Data!$B:$B,IF($F$2="All","*",$F$2)) | C53: =SUMIFS(Data!$E:$E,Data!$A:$A,$A50,Data!$C:$C,"OnlyGuider",Data!$B:$B,IF($F$2="All","*",$F$2)) | D53: =SUMIFS(Data!$F:$F,Data!$A:$A,$A50,Data!$C:$C,"OnlyGuider",Data!$B:$B,IF($F$2="All","*",$F$2)) | E53: =IFERROR(D53/C53,"") | F53: =IFERROR(D53/B53,"") | G53: =IFERROR(C53/B53,"") | H53: =SUMIFS(Data!$G:$G,Data!$A:$A,$A50,Data!$C:$C,"OnlyGuider",Data!$B:$B,IF($F$2="All","*",$F$2)) | I53: =IFERROR(H53/C53,"") | J53: =IFERROR(H53/D53,"") | K53: =H53-D53
A54: OnlySeeker | B54: =SUMIFS(Data!$D:$D,Data!$A:$A,$A50,Data!$C:$C,"OnlySeeker",Data!$B:$B,IF($F$2="All","*",$F$2)) | C54: =SUMIFS(Data!$E:$E,Data!$A:$A,$A50,Data!$C:$C,"OnlySeeker",Data!$B:$B,IF($F$2="All","*",$F$2)) | D54: =SUMIFS(Data!$F:$F,Data!$A:$A,$A50,Data!$C:$C,"OnlySeeker",Data!$B:$B,IF($F$2="All","*",$F$2)) | E54: =IFERROR(D54/C54,"") | F54: =IFERROR(D54/B54,"") | G54: =IFERROR(C54/B54,"") | H54: =SUMIFS(Data!$G:$G,Data!$A:$A,$A50,Data!$C:$C,"OnlySeeker",Data!$B:$B,IF($F$2="All","*",$F$2)) | I54: =IFERROR(H54/C54,"") | J54: =IFERROR(H54/D54,"") | K54: =H54-D54
A55: OnlyTraffic | B55: =SUMIFS(Data!$D:$D,Data!$A:$A,$A50,Data!$C:$C,"OnlyTraffic",Data!$B:$B,IF($F$2="All","*",$F$2)) | C55: =SUMIFS(Data!$E:$E,Data!$A:$A,$A50,Data!$C:$C,"OnlyTraffic",Data!$B:$B,IF($F$2="All","*",$F$2)) | D55: =SUMIFS(Data!$F:$F,Data!$A:$A,$A50,Data!$C:$C,"OnlyTraffic",Data!$B:$B,IF($F$2="All","*",$F$2)) | E55: =IFERROR(D55/C55,"") | F55: =IFERROR(D55/B55,"") | G55: =IFERROR(C55/B55,"") | H55: =SUMIFS(Data!$G:$G,Data!$A:$A,$A50,Data!$C:$C,"OnlyTraffic",Data!$B:$B,IF($F$2="All","*",$F$2)) | I55: =IFERROR(H55/C55,"") | J55: =IFERROR(H55/D55,"") | K55: =H55-D55
A56: =$B$2+7 | B56: =SUMIFS(Data!$D:$D,Data!$A:$A,$A56,Data!$B:$B,IF($F$2="All","*",$F$2)) | C56: =SUMIFS(Data!$E:$E,Data!$A:$A,$A56,Data!$B:$B,IF($F$2="All","*",$F$2)) | D56: =SUMIFS(Data!$F:$F,Data!$A:$A,$A56,Data!$B:$B,IF($F$2="All","*",$F$2)) | E56: =IFERROR(D56/C56,"") | F56: =IFERROR(D56/B56,"") | G56: =IFERROR(C56/B56,"") | H56: =SUMIFS(Data!$G:$G,Data!$A:$A,$A56,Data!$B:$B,IF($F$2="All","*",$F$2)) | I56: =IFERROR(H56/C56,"") | J56: =IFERROR(H56/D56,"") | K56: =H56-D56
A57: Meta | B57: =SUMIFS(Data!$D:$D,Data!$A:$A,$A56,Data!$C:$C,"Meta",Data!$B:$B,IF($F$2="All","*",$F$2)) | C57: =SUMIFS(Data!$E:$E,Data!$A:$A,$A56,Data!$C:$C,"Meta",Data!$B:$B,IF($F$2="All","*",$F$2)) | D57: =SUMIFS(Data!$F:$F,Data!$A:$A,$A56,Data!$C:$C,"Meta",Data!$B:$B,IF($F$2="All","*",$F$2)) | E57: =IFERROR(D57/C57,"") | F57: =IFERROR(D57/B57,"") | G57: =IFERROR(C57/B57,"") | H57: =SUMIFS(Data!$G:$G,Data!$A:$A,$A56,Data!$C:$C,"Meta",Data!$B:$B,IF($F$2="All","*",$F$2)) | I57: =IFERROR(H57/C57,"") | J57: =IFERROR(H57/D57,"") | K57: =H57-D57
A58: OnlyFinder | B58: =SUMIFS(Data!$D:$D,Data!$A:$A,$A56,Data!$C:$C,"OnlyFinder",Data!$B:$B,IF($F$2="All","*",$F$2)) | C58: =SUMIFS(Data!$E:$E,Data!$A:$A,$A56,Data!$C:$C,"OnlyFinder",Data!$B:$B,IF($F$2="All","*",$F$2)) | D58: =SUMIFS(Data!$F:$F,Data!$A:$A,$A56,Data!$C:$C,"OnlyFinder",Data!$B:$B,IF($F$2="All","*",$F$2)) | E58: =IFERROR(D58/C58,"") | F58: =IFERROR(D58/B58,"") | G58: =IFERROR(C58/B58,"") | H58: =SUMIFS(Data!$G:$G,Data!$A:$A,$A56,Data!$C:$C,"OnlyFinder",Data!$B:$B,IF($F$2="All","*",$F$2)) | I58: =IFERROR(H58/C58,"") | J58: =IFERROR(H58/D58,"") | K58: =H58-D58
A59: OnlyGuider | B59: =SUMIFS(Data!$D:$D,Data!$A:$A,$A56,Data!$C:$C,"OnlyGuider",Data!$B:$B,IF($F$2="All","*",$F$2)) | C59: =SUMIFS(Data!$E:$E,Data!$A:$A,$A56,Data!$C:$C,"OnlyGuider",Data!$B:$B,IF($F$2="All","*",$F$2)) | D59: =SUMIFS(Data!$F:$F,Data!$A:$A,$A56,Data!$C:$C,"OnlyGuider",Data!$B:$B,IF($F$2="All","*",$F$2)) | E59: =IFERROR(D59/C59,"") | F59: =IFERROR(D59/B59,"") | G59: =IFERROR(C59/B59,"") | H59: =SUMIFS(Data!$G:$G,Data!$A:$A,$A56,Data!$C:$C,"OnlyGuider",Data!$B:$B,IF($F$2="All","*",$F$2)) | I59: =IFERROR(H59/C59,"") | J59: =IFERROR(H59/D59,"") | K59: =H59-D59
A60: OnlySeeker | B60: =SUMIFS(Data!$D:$D,Data!$A:$A,$A56,Data!$C:$C,"OnlySeeker",Data!$B:$B,IF($F$2="All","*",$F$2)) | C60: =SUMIFS(Data!$E:$E,Data!$A:$A,$A56,Data!$C:$C,"OnlySeeker",Data!$B:$B,IF($F$2="All","*",$F$2)) | D60: =SUMIFS(Data!$F:$F,Data!$A:$A,$A56,Data!$C:$C,"OnlySeeker",Data!$B:$B,IF($F$2="All","*",$F$2)) | E60: =IFERROR(D60/C60,"") | F60: =IFERROR(D60/B60,"") | G60: =IFERROR(C60/B60,"") | H60: =SUMIFS(Data!$G:$G,Data!$A:$A,$A56,Data!$C:$C,"OnlySeeker",Data!$B:$B,IF($F$2="All","*",$F$2)) | I60: =IFERROR(H60/C60,"") | J60: =IFERROR(H60/D60,"") | K60: =H60-D60
A61: OnlyTraffic | B61: =SUMIFS(Data!$D:$D,Data!$A:$A,$A56,Data!$C:$C,"OnlyTraffic",Data!$B:$B,IF($F$2="All","*",$F$2)) | C61: =SUMIFS(Data!$E:$E,Data!$A:$A,$A56,Data!$C:$C,"OnlyTraffic",Data!$B:$B,IF($F$2="All","*",$F$2)) | D61: =SUMIFS(Data!$F:$F,Data!$A:$A,$A56,Data!$C:$C,"OnlyTraffic",Data!$B:$B,IF($F$2="All","*",$F$2)) | E61: =IFERROR(D61/C61,"") | F61: =IFERROR(D61/B61,"") | G61: =IFERROR(C61/B61,"") | H61: =SUMIFS(Data!$G:$G,Data!$A:$A,$A56,Data!$C:$C,"OnlyTraffic",Data!$B:$B,IF($F$2="All","*",$F$2)) | I61: =IFERROR(H61/C61,"") | J61: =IFERROR(H61/D61,"") | K61: =H61-D61
A62: =$B$2+8 | B62: =SUMIFS(Data!$D:$D,Data!$A:$A,$A62,Data!$B:$B,IF($F$2="All","*",$F$2)) | C62: =SUMIFS(Data!$E:$E,Data!$A:$A,$A62,Data!$B:$B,IF($F$2="All","*",$F$2)) | D62: =SUMIFS(Data!$F:$F,Data!$A:$A,$A62,Data!$B:$B,IF($F$2="All","*",$F$2)) | E62: =IFERROR(D62/C62,"") | F62: =IFERROR(D62/B62,"") | G62: =IFERROR(C62/B62,"") | H62: =SUMIFS(Data!$G:$G,Data!$A:$A,$A62,Data!$B:$B,IF($F$2="All","*",$F$2)) | I62: =IFERROR(H62/C62,"") | J62: =IFERROR(H62/D62,"") | K62: =H62-D62
A63: Meta | B63: =SUMIFS(Data!$D:$D,Data!$A:$A,$A62,Data!$C:$C,"Meta",Data!$B:$B,IF($F$2="All","*",$F$2)) | C63: =SUMIFS(Data!$E:$E,Data!$A:$A,$A62,Data!$C:$C,"Meta",Data!$B:$B,IF($F$2="All","*",$F$2)) | D63: =SUMIFS(Data!$F:$F,Data!$A:$A,$A62,Data!$C:$C,"Meta",Data!$B:$B,IF($F$2="All","*",$F$2)) | E63: =IFERROR(D63/C63,"") | F63: =IFERROR(D63/B63,"") | G63: =IFERROR(C63/B63,"") | H63: =SUMIFS(Data!$G:$G,Data!$A:$A,$A62,Data!$C:$C,"Meta",Data!$B:$B,IF($F$2="All","*",$F$2)) | I63: =IFERROR(H63/C63,"") | J63: =IFERROR(H63/D63,"") | K63: =H63-D63
A64: OnlyFinder | B64: =SUMIFS(Data!$D:$D,Data!$A:$A,$A62,Data!$C:$C,"OnlyFinder",Data!$B:$B,IF($F$2="All","*",$F$2)) | C64: =SUMIFS(Data!$E:$E,Data!$A:$A,$A62,Data!$C:$C,"OnlyFinder",Data!$B:$B,IF($F$2="All","*",$F$2)) | D64: =SUMIFS(Data!$F:$F,Data!$A:$A,$A62,Data!$C:$C,"OnlyFinder",Data!$B:$B,IF($F$2="All","*",$F$2)) | E64: =IFERROR(D64/C64,"") | F64: =IFERROR(D64/B64,"") | G64: =IFERROR(C64/B64,"") | H64: =SUMIFS(Data!$G:$G,Data!$A:$A,$A62,Data!$C:$C,"OnlyFinder",Data!$B:$B,IF($F$2="All","*",$F$2)) | I64: =IFERROR(H64/C64,"") | J64: =IFERROR(H64/D64,"") | K64: =H64-D64
A65: OnlyGuider | B65: =SUMIFS(Data!$D:$D,Data!$A:$A,$A62,Data!$C:$C,"OnlyGuider",Data!$B:$B,IF($F$2="All","*",$F$2)) | C65: =SUMIFS(Data!$E:$E,Data!$A:$A,$A62,Data!$C:$C,"OnlyGuider",Data!$B:$B,IF($F$2="All","*",$F$2)) | D65: =SUMIFS(Data!$F:$F,Data!$A:$A,$A62,Data!$C:$C,"OnlyGuider",Data!$B:$B,IF($F$2="All","*",$F$2)) | E65: =IFERROR(D65/C65,"") | F65: =IFERROR(D65/B65,"") | G65: =IFERROR(C65/B65,"") | H65: =SUMIFS(Data!$G:$G,Data!$A:$A,$A62,Data!$C:$C,"OnlyGuider",Data!$B:$B,IF($F$2="All","*",$F$2)) | I65: =IFERROR(H65/C65,"") | J65: =IFERROR(H65/D65,"") | K65: =H65-D65
A66: OnlySeeker | B66: =SUMIFS(Data!$D:$D,Data!$A:$A,$A62,Data!$C:$C,"OnlySeeker",Data!$B:$B,IF($F$2="All","*",$F$2)) | C66: =SUMIFS(Data!$E:$E,Data!$A:$A,$A62,Data!$C:$C,"OnlySeeker",Data!$B:$B,IF($F$2="All","*",$F$2)) | D66: =SUMIFS(Data!$F:$F,Data!$A:$A,$A62,Data!$C:$C,"OnlySeeker",Data!$B:$B,IF($F$2="All","*",$F$2)) | E66: =IFERROR(D66/C66,"") | F66: =IFERROR(D66/B66,"") | G66: =IFERROR(C66/B66,"") | H66: =SUMIFS(Data!$G:$G,Data!$A:$A,$A62,Data!$C:$C,"OnlySeeker",Data!$B:$B,IF($F$2="All","*",$F$2)) | I66: =IFERROR(H66/C66,"") | J66: =IFERROR(H66/D66,"") | K66: =H66-D66
A67: OnlyTraffic | B67: =SUMIFS(Data!$D:$D,Data!$A:$A,$A62,Data!$C:$C,"OnlyTraffic",Data!$B:$B,IF($F$2="All","*",$F$2)) | C67: =SUMIFS(Data!$E:$E,Data!$A:$A,$A62,Data!$C:$C,"OnlyTraffic",Data!$B:$B,IF($F$2="All","*",$F$2)) | D67: =SUMIFS(Data!$F:$F,Data!$A:$A,$A62,Data!$C:$C,"OnlyTraffic",Data!$B:$B,IF($F$2="All","*",$F$2)) | E67: =IFERROR(D67/C67,"") | F67: =IFERROR(D67/B67,"") | G67: =IFERROR(C67/B67,"") | H67: =SUMIFS(Data!$G:$G,Data!$A:$A,$A62,Data!$C:$C,"OnlyTraffic",Data!$B:$B,IF($F$2="All","*",$F$2)) | I67: =IFERROR(H67/C67,"") | J67: =IFERROR(H67/D67,"") | K67: =H67-D67
A68: =$B$2+9 | B68: =SUMIFS(Data!$D:$D,Data!$A:$A,$A68,Data!$B:$B,IF($F$2="All","*",$F$2)) | C68: =SUMIFS(Data!$E:$E,Data!$A:$A,$A68,Data!$B:$B,IF($F$2="All","*",$F$2)) | D68: =SUMIFS(Data!$F:$F,Data!$A:$A,$A68,Data!$B:$B,IF($F$2="All","*",$F$2)) | E68: =IFERROR(D68/C68,"") | F68: =IFERROR(D68/B68,"") | G68: =IFERROR(C68/B68,"") | H68: =SUMIFS(Data!$G:$G,Data!$A:$A,$A68,Data!$B:$B,IF($F$2="All","*",$F$2)) | I68: =IFERROR(H68/C68,"") | J68: =IFERROR(H68/D68,"") | K68: =H68-D68
A69: Meta | B69: =SUMIFS(Data!$D:$D,Data!$A:$A,$A68,Data!$C:$C,"Meta",Data!$B:$B,IF($F$2="All","*",$F$2)) | C69: =SUMIFS(Data!$E:$E,Data!$A:$A,$A68,Data!$C:$C,"Meta",Data!$B:$B,IF($F$2="All","*",$F$2)) | D69: =SUMIFS(Data!$F:$F,Data!$A:$A,$A68,Data!$C:$C,"Meta",Data!$B:$B,IF($F$2="All","*",$F$2)) | E69: =IFERROR(D69/C69,"") | F69: =IFERROR(D69/B69,"") | G69: =IFERROR(C69/B69,"") | H69: =SUMIFS(Data!$G:$G,Data!$A:$A,$A68,Data!$C:$C,"Meta",Data!$B:$B,IF($F$2="All","*",$F$2)) | I69: =IFERROR(H69/C69,"") | J69: =IFERROR(H69/D69,"") | K69: =H69-D69
A70: OnlyFinder | B70: =SUMIFS(Data!$D:$D,Data!$A:$A,$A68,Data!$C:$C,"OnlyFinder",Data!$B:$B,IF($F$2="All","*",$F$2)) | C70: =SUMIFS(Data!$E:$E,Data!$A:$A,$A68,Data!$C:$C,"OnlyFinder",Data!$B:$B,IF($F$2="All","*",$F$2)) | D70: =SUMIFS(Data!$F:$F,Data!$A:$A,$A68,Data!$C:$C,"OnlyFinder",Data!$B:$B,IF($F$2="All","*",$F$2)) | E70: =IFERROR(D70/C70,"") | F70: =IFERROR(D70/B70,"") | G70: =IFERROR(C70/B70,"") | H70: =SUMIFS(Data!$G:$G,Data!$A:$A,$A68,Data!$C:$C,"OnlyFinder",Data!$B:$B,IF($F$2="All","*",$F$2)) | I70: =IFERROR(H70/C70,"") | J70: =IFERROR(H70/D70,"") | K70: =H70-D70
A71: OnlyGuider | B71: =SUMIFS(Data!$D:$D,Data!$A:$A,$A68,Data!$C:$C,"OnlyGuider",Data!$B:$B,IF($F$2="All","*",$F$2)) | C71: =SUMIFS(Data!$E:$E,Data!$A:$A,$A68,Data!$C:$C,"OnlyGuider",Data!$B:$B,IF($F$2="All","*",$F$2)) | D71: =SUMIFS(Data!$F:$F,Data!$A:$A,$A68,Data!$C:$C,"OnlyGuider",Data!$B:$B,IF($F$2="All","*",$F$2)) | E71: =IFERROR(D71/C71,"") | F71: =IFERROR(D71/B71,"") | G71: =IFERROR(C71/B71,"") | H71: =SUMIFS(Data!$G:$G,Data!$A:$A,$A68,Data!$C:$C,"OnlyGuider",Data!$B:$B,IF($F$2="All","*",$F$2)) | I71: =IFERROR(H71/C71,"") | J71: =IFERROR(H71/D71,"") | K71: =H71-D71
A72: OnlySeeker | B72: =SUMIFS(Data!$D:$D,Data!$A:$A,$A68,Data!$C:$C,"OnlySeeker",Data!$B:$B,IF($F$2="All","*",$F$2)) | C72: =SUMIFS(Data!$E:$E,Data!$A:$A,$A68,Data!$C:$C,"OnlySeeker",Data!$B:$B,IF($F$2="All","*",$F$2)) | D72: =SUMIFS(Data!$F:$F,Data!$A:$A,$A68,Data!$C:$C,"OnlySeeker",Data!$B:$B,IF($F$2="All","*",$F$2)) | E72: =IFERROR(D72/C72,"") | F72: =IFERROR(D72/B72,"") | G72: =IFERROR(C72/B72,"") | H72: =SUMIFS(Data!$G:$G,Data!$A:$A,$A68,Data!$C:$C,"OnlySeeker",Data!$B:$B,IF($F$2="All","*",$F$2)) | I72: =IFERROR(H72/C72,"") | J72: =IFERROR(H72/D72,"") | K72: =H72-D72
A73: OnlyTraffic | B73: =SUMIFS(Data!$D:$D,Data!$A:$A,$A68,Data!$C:$C,"OnlyTraffic",Data!$B:$B,IF($F$2="All","*",$F$2)) | C73: =SUMIFS(Data!$E:$E,Data!$A:$A,$A68,Data!$C:$C,"OnlyTraffic",Data!$B:$B,IF($F$2="All","*",$F$2)) | D73: =SUMIFS(Data!$F:$F,Data!$A:$A,$A68,Data!$C:$C,"OnlyTraffic",Data!$B:$B,IF($F$2="All","*",$F$2)) | E73: =IFERROR(D73/C73,"") | F73: =IFERROR(D73/B73,"") | G73: =IFERROR(C73/B73,"") | H73: =SUMIFS(Data!$G:$G,Data!$A:$A,$A68,Data!$C:$C,"OnlyTraffic",Data!$B:$B,IF($F$2="All","*",$F$2)) | I73: =IFERROR(H73/C73,"") | J73: =IFERROR(H73/D73,"") | K73: =H73-D73
A74: =$B$2+10 | B74: =SUMIFS(Data!$D:$D,Data!$A:$A,$A74,Data!$B:$B,IF($F$2="All","*",$F$2)) | C74: =SUMIFS(Data!$E:$E,Data!$A:$A,$A74,Data!$B:$B,IF($F$2="All","*",$F$2)) | D74: =SUMIFS(Data!$F:$F,Data!$A:$A,$A74,Data!$B:$B,IF($F$2="All","*",$F$2)) | E74: =IFERROR(D74/C74,"") | F74: =IFERROR(D74/B74,"") | G74: =IFERROR(C74/B74,"") | H74: =SUMIFS(Data!$G:$G,Data!$A:$A,$A74,Data!$B:$B,IF($F$2="All","*",$F$2)) | I74: =IFERROR(H74/C74,"") | J74: =IFERROR(H74/D74,"") | K74: =H74-D74
A75: Meta | B75: =SUMIFS(Data!$D:$D,Data!$A:$A,$A74,Data!$C:$C,"Meta",Data!$B:$B,IF($F$2="All","*",$F$2)) | C75: =SUMIFS(Data!$E:$E,Data!$A:$A,$A74,Data!$C:$C,"Meta",Data!$B:$B,IF($F$2="All","*",$F$2)) | D75: =SUMIFS(Data!$F:$F,Data!$A:$A,$A74,Data!$C:$C,"Meta",Data!$B:$B,IF($F$2="All","*",$F$2)) | E75: =IFERROR(D75/C75,"") | F75: =IFERROR(D75/B75,"") | G75: =IFERROR(C75/B75,"") | H75: =SUMIFS(Data!$G:$G,Data!$A:$A,$A74,Data!$C:$C,"Meta",Data!$B:$B,IF($F$2="All","*",$F$2)) | I75: =IFERROR(H75/C75,"") | J75: =IFERROR(H75/D75,"") | K75: =H75-D75
A76: OnlyFinder | B76: =SUMIFS(Data!$D:$D,Data!$A:$A,$A74,Data!$C:$C,"OnlyFinder",Data!$B:$B,IF($F$2="All","*",$F$2)) | C76: =SUMIFS(Data!$E:$E,Data!$A:$A,$A74,Data!$C:$C,"OnlyFinder",Data!$B:$B,IF($F$2="All","*",$F$2)) | D76: =SUMIFS(Data!$F:$F,Data!$A:$A,$A74,Data!$C:$C,"OnlyFinder",Data!$B:$B,IF($F$2="All","*",$F$2)) | E76: =IFERROR(D76/C76,"") | F76: =IFERROR(D76/B76,"") | G76: =IFERROR(C76/B76,"") | H76: =SUMIFS(Data!$G:$G,Data!$A:$A,$A74,Data!$C:$C,"OnlyFinder",Data!$B:$B,IF($F$2="All","*",$F$2)) | I76: =IFERROR(H76/C76,"") | J76: =IFERROR(H76/D76,"") | K76: =H76-D76
A77: OnlyGuider | B77: =SUMIFS(Data!$D:$D,Data!$A:$A,$A74,Data!$C:$C,"OnlyGuider",Data!$B:$B,IF($F$2="All","*",$F$2)) | C77: =SUMIFS(Data!$E:$E,Data!$A:$A,$A74,Data!$C:$C,"OnlyGuider",Data!$B:$B,IF($F$2="All","*",$F$2)) | D77: =SUMIFS(Data!$F:$F,Data!$A:$A,$A74,Data!$C:$C,"OnlyGuider",Data!$B:$B,IF($F$2="All","*",$F$2)) | E77: =IFERROR(D77/C77,"") | F77: =IFERROR(D77/B77,"") | G77: =IFERROR(C77/B77,"") | H77: =SUMIFS(Data!$G:$G,Data!$A:$A,$A74,Data!$C:$C,"OnlyGuider",Data!$B:$B,IF($F$2="All","*",$F$2)) | I77: =IFERROR(H77/C77,"") | J77: =IFERROR(H77/D77,"") | K77: =H77-D77
A78: OnlySeeker | B78: =SUMIFS(Data!$D:$D,Data!$A:$A,$A74,Data!$C:$C,"OnlySeeker",Data!$B:$B,IF($F$2="All","*",$F$2)) | C78: =SUMIFS(Data!$E:$E,Data!$A:$A,$A74,Data!$C:$C,"OnlySeeker",Data!$B:$B,IF($F$2="All","*",$F$2)) | D78: =SUMIFS(Data!$F:$F,Data!$A:$A,$A74,Data!$C:$C,"OnlySeeker",Data!$B:$B,IF($F$2="All","*",$F$2)) | E78: =IFERROR(D78/C78,"") | F78: =IFERROR(D78/B78,"") | G78: =IFERROR(C78/B78,"") | H78: =SUMIFS(Data!$G:$G,Data!$A:$A,$A74,Data!$C:$C,"OnlySeeker",Data!$B:$B,IF($F$2="All","*",$F$2)) | I78: =IFERROR(H78/C78,"") | J78: =IFERROR(H78/D78,"") | K78: =H78-D78
A79: OnlyTraffic | B79: =SUMIFS(Data!$D:$D,Data!$A:$A,$A74,Data!$C:$C,"OnlyTraffic",Data!$B:$B,IF($F$2="All","*",$F$2)) | C79: =SUMIFS(Data!$E:$E,Data!$A:$A,$A74,Data!$C:$C,"OnlyTraffic",Data!$B:$B,IF($F$2="All","*",$F$2)) | D79: =SUMIFS(Data!$F:$F,Data!$A:$A,$A74,Data!$C:$C,"OnlyTraffic",Data!$B:$B,IF($F$2="All","*",$F$2)) | E79: =IFERROR(D79/C79,"") | F79: =IFERROR(D79/B79,"") | G79: =IFERROR(C79/B79,"") | H79: =SUMIFS(Data!$G:$G,Data!$A:$A,$A74,Data!$C:$C,"OnlyTraffic",Data!$B:$B,IF($F$2="All","*",$F$2)) | I79: =IFERROR(H79/C79,"") | J79: =IFERROR(H79/D79,"") | K79: =H79-D79
A80: =$B$2+11 | B80: =SUMIFS(Data!$D:$D,Data!$A:$A,$A80,Data!$B:$B,IF($F$2="All","*",$F$2)) | C80: =SUMIFS(Data!$E:$E,Data!$A:$A,$A80,Data!$B:$B,IF($F$2="All","*",$F$2)) | D80: =SUMIFS(Data!$F:$F,Data!$A:$A,$A80,Data!$B:$B,IF($F$2="All","*",$F$2)) | E80: =IFERROR(D80/C80,"") | F80: =IFERROR(D80/B80,"") | G80: =IFERROR(C80/B80,"") | H80: =SUMIFS(Data!$G:$G,Data!$A:$A,$A80,Data!$B:$B,IF($F$2="All","*",$F$2)) | I80: =IFERROR(H80/C80,"") | J80: =IFERROR(H80/D80,"") | K80: =H80-D80
A81: Meta | B81: =SUMIFS(Data!$D:$D,Data!$A:$A,$A80,Data!$C:$C,"Meta",Data!$B:$B,IF($F$2="All","*",$F$2)) | C81: =SUMIFS(Data!$E:$E,Data!$A:$A,$A80,Data!$C:$C,"Meta",Data!$B:$B,IF($F$2="All","*",$F$2)) | D81: =SUMIFS(Data!$F:$F,Data!$A:$A,$A80,Data!$C:$C,"Meta",Data!$B:$B,IF($F$2="All","*",$F$2)) | E81: =IFERROR(D81/C81,"") | F81: =IFERROR(D81/B81,"") | G81: =IFERROR(C81/B81,"") | H81: =SUMIFS(Data!$G:$G,Data!$A:$A,$A80,Data!$C:$C,"Meta",Data!$B:$B,IF($F$2="All","*",$F$2)) | I81: =IFERROR(H81/C81,"") | J81: =IFERROR(H81/D81,"") | K81: =H81-D81
A82: OnlyFinder | B82: =SUMIFS(Data!$D:$D,Data!$A:$A,$A80,Data!$C:$C,"OnlyFinder",Data!$B:$B,IF($F$2="All","*",$F$2)) | C82: =SUMIFS(Data!$E:$E,Data!$A:$A,$A80,Data!$C:$C,"OnlyFinder",Data!$B:$B,IF($F$2="All","*",$F$2)) | D82: =SUMIFS(Data!$F:$F,Data!$A:$A,$A80,Data!$C:$C,"OnlyFinder",Data!$B:$B,IF($F$2="All","*",$F$2)) | E82: =IFERROR(D82/C82,"") | F82: =IFERROR(D82/B82,"") | G82: =IFERROR(C82/B82,"") | H82: =SUMIFS(Data!$G:$G,Data!$A:$A,$A80,Data!$C:$C,"OnlyFinder",Data!$B:$B,IF($F$2="All","*",$F$2)) | I82: =IFERROR(H82/C82,"") | J82: =IFERROR(H82/D82,"") | K82: =H82-D82
A83: OnlyGuider | B83: =SUMIFS(Data!$D:$D,Data!$A:$A,$A80,Data!$C:$C,"OnlyGuider",Data!$B:$B,IF($F$2="All","*",$F$2)) | C83: =SUMIFS(Data!$E:$E,Data!$A:$A,$A80,Data!$C:$C,"OnlyGuider",Data!$B:$B,IF($F$2="All","*",$F$2)) | D83: =SUMIFS(Data!$F:$F,Data!$A:$A,$A80,Data!$C:$C,"OnlyGuider",Data!$B:$B,IF($F$2="All","*",$F$2)) | E83: =IFERROR(D83/C83,"") | F83: =IFERROR(D83/B83,"") | G83: =IFERROR(C83/B83,"") | H83: =SUMIFS(Data!$G:$G,Data!$A:$A,$A80,Data!$C:$C,"OnlyGuider",Data!$B:$B,IF($F$2="All","*",$F$2)) | I83: =IFERROR(H83/C83,"") | J83: =IFERROR(H83/D83,"") | K83: =H83-D83
A84: OnlySeeker | B84: =SUMIFS(Data!$D:$D,Data!$A:$A,$A80,Data!$C:$C,"OnlySeeker",Data!$B:$B,IF($F$2="All","*",$F$2)) | C84: =SUMIFS(Data!$E:$E,Data!$A:$A,$A80,Data!$C:$C,"OnlySeeker",Data!$B:$B,IF($F$2="All","*",$F$2)) | D84: =SUMIFS(Data!$F:$F,Data!$A:$A,$A80,Data!$C:$C,"OnlySeeker",Data!$B:$B,IF($F$2="All","*",$F$2)) | E84: =IFERROR(D84/C84,"") | F84: =IFERROR(D84/B84,"") | G84: =IFERROR(C84/B84,"") | H84: =SUMIFS(Data!$G:$G,Data!$A:$A,$A80,Data!$C:$C,"OnlySeeker",Data!$B:$B,IF($F$2="All","*",$F$2)) | I84: =IFERROR(H84/C84,"") | J84: =IFERROR(H84/D84,"") | K84: =H84-D84
A85: OnlyTraffic | B85: =SUMIFS(Data!$D:$D,Data!$A:$A,$A80,Data!$C:$C,"OnlyTraffic",Data!$B:$B,IF($F$2="All","*",$F$2)) | C85: =SUMIFS(Data!$E:$E,Data!$A:$A,$A80,Data!$C:$C,"OnlyTraffic",Data!$B:$B,IF($F$2="All","*",$F$2)) | D85: =SUMIFS(Data!$F:$F,Data!$A:$A,$A80,Data!$C:$C,"OnlyTraffic",Data!$B:$B,IF($F$2="All","*",$F$2)) | E85: =IFERROR(D85/C85,"") | F85: =IFERROR(D85/B85,"") | G85: =IFERROR(C85/B85,"") | H85: =SUMIFS(Data!$G:$G,Data!$A:$A,$A80,Data!$C:$C,"OnlyTraffic",Data!$B:$B,IF($F$2="All","*",$F$2)) | I85: =IFERROR(H85/C85,"") | J85: =IFERROR(H85/D85,"") | K85: =H85-D85
A86: =$B$2+12 | B86: =SUMIFS(Data!$D:$D,Data!$A:$A,$A86,Data!$B:$B,IF($F$2="All","*",$F$2)) | C86: =SUMIFS(Data!$E:$E,Data!$A:$A,$A86,Data!$B:$B,IF($F$2="All","*",$F$2)) | D86: =SUMIFS(Data!$F:$F,Data!$A:$A,$A86,Data!$B:$B,IF($F$2="All","*",$F$2)) | E86: =IFERROR(D86/C86,"") | F86: =IFERROR(D86/B86,"") | G86: =IFERROR(C86/B86,"") | H86: =SUMIFS(Data!$G:$G,Data!$A:$A,$A86,Data!$B:$B,IF($F$2="All","*",$F$2)) | I86: =IFERROR(H86/C86,"") | J86: =IFERROR(H86/D86,"") | K86: =H86-D86
A87: Meta | B87: =SUMIFS(Data!$D:$D,Data!$A:$A,$A86,Data!$C:$C,"Meta",Data!$B:$B,IF($F$2="All","*",$F$2)) | C87: =SUMIFS(Data!$E:$E,Data!$A:$A,$A86,Data!$C:$C,"Meta",Data!$B:$B,IF($F$2="All","*",$F$2)) | D87: =SUMIFS(Data!$F:$F,Data!$A:$A,$A86,Data!$C:$C,"Meta",Data!$B:$B,IF($F$2="All","*",$F$2)) | E87: =IFERROR(D87/C87,"") | F87: =IFERROR(D87/B87,"") | G87: =IFERROR(C87/B87,"") | H87: =SUMIFS(Data!$G:$G,Data!$A:$A,$A86,Data!$C:$C,"Meta",Data!$B:$B,IF($F$2="All","*",$F$2)) | I87: =IFERROR(H87/C87,"") | J87: =IFERROR(H87/D87,"") | K87: =H87-D87
A88: OnlyFinder | B88: =SUMIFS(Data!$D:$D,Data!$A:$A,$A86,Data!$C:$C,"OnlyFinder",Data!$B:$B,IF($F$2="All","*",$F$2)) | C88: =SUMIFS(Data!$E:$E,Data!$A:$A,$A86,Data!$C:$C,"OnlyFinder",Data!$B:$B,IF($F$2="All","*",$F$2)) | D88: =SUMIFS(Data!$F:$F,Data!$A:$A,$A86,Data!$C:$C,"OnlyFinder",Data!$B:$B,IF($F$2="All","*",$F$2)) | E88: =IFERROR(D88/C88,"") | F88: =IFERROR(D88/B88,"") | G88: =IFERROR(C88/B88,"") | H88: =SUMIFS(Data!$G:$G,Data!$A:$A,$A86,Data!$C:$C,"OnlyFinder",Data!$B:$B,IF($F$2="All","*",$F$2)) | I88: =IFERROR(H88/C88,"") | J88: =IFERROR(H88/D88,"") | K88: =H88-D88
A89: OnlyGuider | B89: =SUMIFS(Data!$D:$D,Data!$A:$A,$A86,Data!$C:$C,"OnlyGuider",Data!$B:$B,IF($F$2="All","*",$F$2)) | C89: =SUMIFS(Data!$E:$E,Data!$A:$A,$A86,Data!$C:$C,"OnlyGuider",Data!$B:$B,IF($F$2="All","*",$F$2)) | D89: =SUMIFS(Data!$F:$F,Data!$A:$A,$A86,Data!$C:$C,"OnlyGuider",Data!$B:$B,IF($F$2="All","*",$F$2)) | E89: =IFERROR(D89/C89,"") | F89: =IFERROR(D89/B89,"") | G89: =IFERROR(C89/B89,"") | H89: =SUMIFS(Data!$G:$G,Data!$A:$A,$A86,Data!$C:$C,"OnlyGuider",Data!$B:$B,IF($F$2="All","*",$F$2)) | I89: =IFERROR(H89/C89,"") | J89: =IFERROR(H89/D89,"") | K89: =H89-D89
A90: OnlySeeker | B90: =SUMIFS(Data!$D:$D,Data!$A:$A,$A86,Data!$C:$C,"OnlySeeker",Data!$B:$B,IF($F$2="All","*",$F$2)) | C90: =SUMIFS(Data!$E:$E,Data!$A:$A,$A86,Data!$C:$C,"OnlySeeker",Data!$B:$B,IF($F$2="All","*",$F$2)) | D90: =SUMIFS(Data!$F:$F,Data!$A:$A,$A86,Data!$C:$C,"OnlySeeker",Data!$B:$B,IF($F$2="All","*",$F$2)) | E90: =IFERROR(D90/C90,"") | F90: =IFERROR(D90/B90,"") | G90: =IFERROR(C90/B90,"") | H90: =SUMIFS(Data!$G:$G,Data!$A:$A,$A86,Data!$C:$C,"OnlySeeker",Data!$B:$B,IF($F$2="All","*",$F$2)) | I90: =IFERROR(H90/C90,"") | J90: =IFERROR(H90/D90,"") | K90: =H90-D90
A91: OnlyTraffic | B91: =SUMIFS(Data!$D:$D,Data!$A:$A,$A86,Data!$C:$C,"OnlyTraffic",Data!$B:$B,IF($F$2="All","*",$F$2)) | C91: =SUMIFS(Data!$E:$E,Data!$A:$A,$A86,Data!$C:$C,"OnlyTraffic",Data!$B:$B,IF($F$2="All","*",$F$2)) | D91: =SUMIFS(Data!$F:$F,Data!$A:$A,$A86,Data!$C:$C,"OnlyTraffic",Data!$B:$B,IF($F$2="All","*",$F$2)) | E91: =IFERROR(D91/C91,"") | F91: =IFERROR(D91/B91,"") | G91: =IFERROR(C91/B91,"") | H91: =SUMIFS(Data!$G:$G,Data!$A:$A,$A86,Data!$C:$C,"OnlyTraffic",Data!$B:$B,IF($F$2="All","*",$F$2)) | I91: =IFERROR(H91/C91,"") | J91: =IFERROR(H91/D91,"") | K91: =H91-D91
A92: =$B$2+13 | B92: =SUMIFS(Data!$D:$D,Data!$A:$A,$A92,Data!$B:$B,IF($F$2="All","*",$F$2)) | C92: =SUMIFS(Data!$E:$E,Data!$A:$A,$A92,Data!$B:$B,IF($F$2="All","*",$F$2)) | D92: =SUMIFS(Data!$F:$F,Data!$A:$A,$A92,Data!$B:$B,IF($F$2="All","*",$F$2)) | E92: =IFERROR(D92/C92,"") | F92: =IFERROR(D92/B92,"") | G92: =IFERROR(C92/B92,"") | H92: =SUMIFS(Data!$G:$G,Data!$A:$A,$A92,Data!$B:$B,IF($F$2="All","*",$F$2)) | I92: =IFERROR(H92/C92,"") | J92: =IFERROR(H92/D92,"") | K92: =H92-D92
A93: Meta | B93: =SUMIFS(Data!$D:$D,Data!$A:$A,$A92,Data!$C:$C,"Meta",Data!$B:$B,IF($F$2="All","*",$F$2)) | C93: =SUMIFS(Data!$E:$E,Data!$A:$A,$A92,Data!$C:$C,"Meta",Data!$B:$B,IF($F$2="All","*",$F$2)) | D93: =SUMIFS(Data!$F:$F,Data!$A:$A,$A92,Data!$C:$C,"Meta",Data!$B:$B,IF($F$2="All","*",$F$2)) | E93: =IFERROR(D93/C93,"") | F93: =IFERROR(D93/B93,"") | G93: =IFERROR(C93/B93,"") | H93: =SUMIFS(Data!$G:$G,Data!$A:$A,$A92,Data!$C:$C,"Meta",Data!$B:$B,IF($F$2="All","*",$F$2)) | I93: =IFERROR(H93/C93,"") | J93: =IFERROR(H93/D93,"") | K93: =H93-D93
A94: OnlyFinder | B94: =SUMIFS(Data!$D:$D,Data!$A:$A,$A92,Data!$C:$C,"OnlyFinder",Data!$B:$B,IF($F$2="All","*",$F$2)) | C94: =SUMIFS(Data!$E:$E,Data!$A:$A,$A92,Data!$C:$C,"OnlyFinder",Data!$B:$B,IF($F$2="All","*",$F$2)) | D94: =SUMIFS(Data!$F:$F,Data!$A:$A,$A92,Data!$C:$C,"OnlyFinder",Data!$B:$B,IF($F$2="All","*",$F$2)) | E94: =IFERROR(D94/C94,"") | F94: =IFERROR(D94/B94,"") | G94: =IFERROR(C94/B94,"") | H94: =SUMIFS(Data!$G:$G,Data!$A:$A,$A92,Data!$C:$C,"OnlyFinder",Data!$B:$B,IF($F$2="All","*",$F$2)) | I94: =IFERROR(H94/C94,"") | J94: =IFERROR(H94/D94,"") | K94: =H94-D94
A95: OnlyGuider | B95: =SUMIFS(Data!$D:$D,Data!$A:$A,$A92,Data!$C:$C,"OnlyGuider",Data!$B:$B,IF($F$2="All","*",$F$2)) | C95: =SUMIFS(Data!$E:$E,Data!$A:$A,$A92,Data!$C:$C,"OnlyGuider",Data!$B:$B,IF($F$2="All","*",$F$2)) | D95: =SUMIFS(Data!$F:$F,Data!$A:$A,$A92,Data!$C:$C,"OnlyGuider",Data!$B:$B,IF($F$2="All","*",$F$2)) | E95: =IFERROR(D95/C95,"") | F95: =IFERROR(D95/B95,"") | G95: =IFERROR(C95/B95,"") | H95: =SUMIFS(Data!$G:$G,Data!$A:$A,$A92,Data!$C:$C,"OnlyGuider",Data!$B:$B,IF($F$2="All","*",$F$2)) | I95: =IFERROR(H95/C95,"") | J95: =IFERROR(H95/D95,"") | K95: =H95-D95
A96: OnlySeeker | B96: =SUMIFS(Data!$D:$D,Data!$A:$A,$A92,Data!$C:$C,"OnlySeeker",Data!$B:$B,IF($F$2="All","*",$F$2)) | C96: =SUMIFS(Data!$E:$E,Data!$A:$A,$A92,Data!$C:$C,"OnlySeeker",Data!$B:$B,IF($F$2="All","*",$F$2)) | D96: =SUMIFS(Data!$F:$F,Data!$A:$A,$A92,Data!$C:$C,"OnlySeeker",Data!$B:$B,IF($F$2="All","*",$F$2)) | E96: =IFERROR(D96/C96,"") | F96: =IFERROR(D96/B96,"") | G96: =IFERROR(C96/B96,"") | H96: =SUMIFS(Data!$G:$G,Data!$A:$A,$A92,Data!$C:$C,"OnlySeeker",Data!$B:$B,IF($F$2="All","*",$F$2)) | I96: =IFERROR(H96/C96,"") | J96: =IFERROR(H96/D96,"") | K96: =H96-D96
A97: OnlyTraffic | B97: =SUMIFS(Data!$D:$D,Data!$A:$A,$A92,Data!$C:$C,"OnlyTraffic",Data!$B:$B,IF($F$2="All","*",$F$2)) | C97: =SUMIFS(Data!$E:$E,Data!$A:$A,$A92,Data!$C:$C,"OnlyTraffic",Data!$B:$B,IF($F$2="All","*",$F$2)) | D97: =SUMIFS(Data!$F:$F,Data!$A:$A,$A92,Data!$C:$C,"OnlyTraffic",Data!$B:$B,IF($F$2="All","*",$F$2)) | E97: =IFERROR(D97/C97,"") | F97: =IFERROR(D97/B97,"") | G97: =IFERROR(C97/B97,"") | H97: =SUMIFS(Data!$G:$G,Data!$A:$A,$A92,Data!$C:$C,"OnlyTraffic",Data!$B:$B,IF($F$2="All","*",$F$2)) | I97: =IFERROR(H97/C97,"") | J97: =IFERROR(H97/D97,"") | K97: =H97-D97

Sheet Time to Profit
A1: UNCVRD — TIME TO PROFIT / BREAK-EVEN (per platform · lifetime value of the fans each platform brought)
A2: Creator ▸ | B2: All | D2: Set each platform's REAL Cost / Click in the yellow column (D) below — Meta, OnlyFinder etc. can each have their own rate →
A3: ARPS = revenue each fan has spent by that age. Profitable when ARPS All ≥ Cost / Sub. Green margin = you make money.
A4: Platform | B4: Subscribers | C4: Clicks | D4: Cost / Click | E4: Cost / Promo | F4: Cost / Sub | G4: ARPS 48h | H4: ARPS 7d | I4: ARPS 14d | J4: ARPS 30d | K4: ARPS All (Rev/Sub) | L4: Margin / Sub | M4: Break-even by
A5: Meta | B5: =SUMIFS(Cohort!$C:$C,Cohort!$B:$B,"Meta",Cohort!$A:$A,IF($B$2="All","*",$B$2)) | C5: =SUMIFS(Cohort!$D:$D,Cohort!$B:$B,"Meta",Cohort!$A:$A,IF($B$2="All","*",$B$2)) | D5: 0.75 | E5: =D5*C5 | F5: =IFERROR(E5/B5,"") | G5: =IFERROR((SUMIFS(Cohort!$E:$E,Cohort!$B:$B,"Meta",Cohort!$A:$A,IF($B$2="All","*",$B$2)))/B5,"") | H5: =IFERROR((SUMIFS(Cohort!$F:$F,Cohort!$B:$B,"Meta",Cohort!$A:$A,IF($B$2="All","*",$B$2)))/B5,"") | I5: =IFERROR((SUMIFS(Cohort!$G:$G,Cohort!$B:$B,"Meta",Cohort!$A:$A,IF($B$2="All","*",$B$2)))/B5,"") | J5: =IFERROR((SUMIFS(Cohort!$I:$I,Cohort!$B:$B,"Meta",Cohort!$A:$A,IF($B$2="All","*",$B$2)))/B5,"") | K5: =IFERROR((SUMIFS(Cohort!$J:$J,Cohort!$B:$B,"Meta",Cohort!$A:$A,IF($B$2="All","*",$B$2)))/B5,"") | L5: =IFERROR(K5-F5,"") | M5: =IF(B5=0,"",IF(G5>=F5,"by 48h",IF(H5>=F5,"by 7d",IF(I5>=F5,"by 14d",IF(J5>=F5,"by 30d",IF(K5>=F5,"after 30d","not yet"))))))
A6: OnlyFinder | B6: =SUMIFS(Cohort!$C:$C,Cohort!$B:$B,"OnlyFinder",Cohort!$A:$A,IF($B$2="All","*",$B$2)) | C6: =SUMIFS(Cohort!$D:$D,Cohort!$B:$B,"OnlyFinder",Cohort!$A:$A,IF($B$2="All","*",$B$2)) | D6: 0.75 | E6: =D6*C6 | F6: =IFERROR(E6/B6,"") | G6: =IFERROR((SUMIFS(Cohort!$E:$E,Cohort!$B:$B,"OnlyFinder",Cohort!$A:$A,IF($B$2="All","*",$B$2)))/B6,"") | H6: =IFERROR((SUMIFS(Cohort!$F:$F,Cohort!$B:$B,"OnlyFinder",Cohort!$A:$A,IF($B$2="All","*",$B$2)))/B6,"") | I6: =IFERROR((SUMIFS(Cohort!$G:$G,Cohort!$B:$B,"OnlyFinder",Cohort!$A:$A,IF($B$2="All","*",$B$2)))/B6,"") | J6: =IFERROR((SUMIFS(Cohort!$I:$I,Cohort!$B:$B,"OnlyFinder",Cohort!$A:$A,IF($B$2="All","*",$B$2)))/B6,"") | K6: =IFERROR((SUMIFS(Cohort!$J:$J,Cohort!$B:$B,"OnlyFinder",Cohort!$A:$A,IF($B$2="All","*",$B$2)))/B6,"") | L6: =IFERROR(K6-F6,"") | M6: =IF(B6=0,"",IF(G6>=F6,"by 48h",IF(H6>=F6,"by 7d",IF(I6>=F6,"by 14d",IF(J6>=F6,"by 30d",IF(K6>=F6,"after 30d","not yet"))))))
A7: OnlyGuider | B7: =SUMIFS(Cohort!$C:$C,Cohort!$B:$B,"OnlyGuider",Cohort!$A:$A,IF($B$2="All","*",$B$2)) | C7: =SUMIFS(Cohort!$D:$D,Cohort!$B:$B,"OnlyGuider",Cohort!$A:$A,IF($B$2="All","*",$B$2)) | D7: 0.75 | E7: =D7*C7 | F7: =IFERROR(E7/B7,"") | G7: =IFERROR((SUMIFS(Cohort!$E:$E,Cohort!$B:$B,"OnlyGuider",Cohort!$A:$A,IF($B$2="All","*",$B$2)))/B7,"") | H7: =IFERROR((SUMIFS(Cohort!$F:$F,Cohort!$B:$B,"OnlyGuider",Cohort!$A:$A,IF($B$2="All","*",$B$2)))/B7,"") | I7: =IFERROR((SUMIFS(Cohort!$G:$G,Cohort!$B:$B,"OnlyGuider",Cohort!$A:$A,IF($B$2="All","*",$B$2)))/B7,"") | J7: =IFERROR((SUMIFS(Cohort!$I:$I,Cohort!$B:$B,"OnlyGuider",Cohort!$A:$A,IF($B$2="All","*",$B$2)))/B7,"") | K7: =IFERROR((SUMIFS(Cohort!$J:$J,Cohort!$B:$B,"OnlyGuider",Cohort!$A:$A,IF($B$2="All","*",$B$2)))/B7,"") | L7: =IFERROR(K7-F7,"") | M7: =IF(B7=0,"",IF(G7>=F7,"by 48h",IF(H7>=F7,"by 7d",IF(I7>=F7,"by 14d",IF(J7>=F7,"by 30d",IF(K7>=F7,"after 30d","not yet"))))))
A8: OnlySeeker | B8: =SUMIFS(Cohort!$C:$C,Cohort!$B:$B,"OnlySeeker",Cohort!$A:$A,IF($B$2="All","*",$B$2)) | C8: =SUMIFS(Cohort!$D:$D,Cohort!$B:$B,"OnlySeeker",Cohort!$A:$A,IF($B$2="All","*",$B$2)) | D8: 0.75 | E8: =D8*C8 | F8: =IFERROR(E8/B8,"") | G8: =IFERROR((SUMIFS(Cohort!$E:$E,Cohort!$B:$B,"OnlySeeker",Cohort!$A:$A,IF($B$2="All","*",$B$2)))/B8,"") | H8: =IFERROR((SUMIFS(Cohort!$F:$F,Cohort!$B:$B,"OnlySeeker",Cohort!$A:$A,IF($B$2="All","*",$B$2)))/B8,"") | I8: =IFERROR((SUMIFS(Cohort!$G:$G,Cohort!$B:$B,"OnlySeeker",Cohort!$A:$A,IF($B$2="All","*",$B$2)))/B8,"") | J8: =IFERROR((SUMIFS(Cohort!$I:$I,Cohort!$B:$B,"OnlySeeker",Cohort!$A:$A,IF($B$2="All","*",$B$2)))/B8,"") | K8: =IFERROR((SUMIFS(Cohort!$J:$J,Cohort!$B:$B,"OnlySeeker",Cohort!$A:$A,IF($B$2="All","*",$B$2)))/B8,"") | L8: =IFERROR(K8-F8,"") | M8: =IF(B8=0,"",IF(G8>=F8,"by 48h",IF(H8>=F8,"by 7d",IF(I8>=F8,"by 14d",IF(J8>=F8,"by 30d",IF(K8>=F8,"after 30d","not yet"))))))
A9: OnlyTraffic | B9: =SUMIFS(Cohort!$C:$C,Cohort!$B:$B,"OnlyTraffic",Cohort!$A:$A,IF($B$2="All","*",$B$2)) | C9: =SUMIFS(Cohort!$D:$D,Cohort!$B:$B,"OnlyTraffic",Cohort!$A:$A,IF($B$2="All","*",$B$2)) | D9: 0.75 | E9: =D9*C9 | F9: =IFERROR(E9/B9,"") | G9: =IFERROR((SUMIFS(Cohort!$E:$E,Cohort!$B:$B,"OnlyTraffic",Cohort!$A:$A,IF($B$2="All","*",$B$2)))/B9,"") | H9: =IFERROR((SUMIFS(Cohort!$F:$F,Cohort!$B:$B,"OnlyTraffic",Cohort!$A:$A,IF($B$2="All","*",$B$2)))/B9,"") | I9: =IFERROR((SUMIFS(Cohort!$G:$G,Cohort!$B:$B,"OnlyTraffic",Cohort!$A:$A,IF($B$2="All","*",$B$2)))/B9,"") | J9: =IFERROR((SUMIFS(Cohort!$I:$I,Cohort!$B:$B,"OnlyTraffic",Cohort!$A:$A,IF($B$2="All","*",$B$2)))/B9,"") | K9: =IFERROR((SUMIFS(Cohort!$J:$J,Cohort!$B:$B,"OnlyTraffic",Cohort!$A:$A,IF($B$2="All","*",$B$2)))/B9,"") | L9: =IFERROR(K9-F9,"") | M9: =IF(B9=0,"",IF(G9>=F9,"by 48h",IF(H9>=F9,"by 7d",IF(I9>=F9,"by 14d",IF(J9>=F9,"by 30d",IF(K9>=F9,"after 30d","not yet"))))))
A10: TOTAL | B10: =SUMIFS(Cohort!$C:$C,Cohort!$A:$A,IF($B$2="All","*",$B$2)) | C10: =SUMIFS(Cohort!$D:$D,Cohort!$A:$A,IF($B$2="All","*",$B$2)) | D10: =IFERROR(E10/C10,"") | E10: =SUM(E5:E9) | F10: =IFERROR(E10/B10,"") | G10: =IFERROR((SUMIFS(Cohort!$E:$E,Cohort!$A:$A,IF($B$2="All","*",$B$2)))/B10,"") | H10: =IFERROR((SUMIFS(Cohort!$F:$F,Cohort!$A:$A,IF($B$2="All","*",$B$2)))/B10,"") | I10: =IFERROR((SUMIFS(Cohort!$G:$G,Cohort!$A:$A,IF($B$2="All","*",$B$2)))/B10,"") | J10: =IFERROR((SUMIFS(Cohort!$I:$I,Cohort!$A:$A,IF($B$2="All","*",$B$2)))/B10,"") | K10: =IFERROR((SUMIFS(Cohort!$J:$J,Cohort!$A:$A,IF($B$2="All","*",$B$2)))/B10,"") | L10: =IFERROR(K10-F10,"") | M10: =IF(B10=0,"",IF(G10>=F10,"by 48h",IF(H10>=F10,"by 7d",IF(I10>=F10,"by 14d",IF(J10>=F10,"by 30d",IF(K10>=F10,"after 30d","not yet"))))))

Sheet Weekly History
A1: UNCVRD — WEEKLY HISTORY (every week saved · Fri → Thu)
A2: Creator ▸ | B2: All
A3: Week (Fri start) | B3: Clicks | C3: Fans | D3: Spend | E3: CPC | F3: CVR | G3: Attributed Revenue | H3: ROAS | I3: Agency Profit
A4: 46199 | B4: =SUMIFS(Data!$D:$D,Data!$A:$A,">="&$A4,Data!$A:$A,"<="&($A4+6),Data!$B:$B,IF($B$2="All","*",$B$2)) | C4: =SUMIFS(Data!$E:$E,Data!$A:$A,">="&$A4,Data!$A:$A,"<="&($A4+6),Data!$B:$B,IF($B$2="All","*",$B$2)) | D4: =SUMIFS(Data!$F:$F,Data!$A:$A,">="&$A4,Data!$A:$A,"<="&($A4+6),Data!$B:$B,IF($B$2="All","*",$B$2)) | E4: =IFERROR(D4/B4,"") | F4: =IFERROR(C4/B4,"") | G4: =SUMIFS(Data!$G:$G,Data!$A:$A,">="&$A4,Data!$A:$A,"<="&($A4+6),Data!$B:$B,IF($B$2="All","*",$B$2)) | H4: =IFERROR(G4/D4,"") | I4: =G4-D4
A5: 46192 | B5: =SUMIFS(Data!$D:$D,Data!$A:$A,">="&$A5,Data!$A:$A,"<="&($A5+6),Data!$B:$B,IF($B$2="All","*",$B$2)) | C5: =SUMIFS(Data!$E:$E,Data!$A:$A,">="&$A5,Data!$A:$A,"<="&($A5+6),Data!$B:$B,IF($B$2="All","*",$B$2)) | D5: =SUMIFS(Data!$F:$F,Data!$A:$A,">="&$A5,Data!$A:$A,"<="&($A5+6),Data!$B:$B,IF($B$2="All","*",$B$2)) | E5: =IFERROR(D5/B5,"") | F5: =IFERROR(C5/B5,"") | G5: =SUMIFS(Data!$G:$G,Data!$A:$A,">="&$A5,Data!$A:$A,"<="&($A5+6),Data!$B:$B,IF($B$2="All","*",$B$2)) | H5: =IFERROR(G5/D5,"") | I5: =G5-D5
A6: 46185 | B6: =SUMIFS(Data!$D:$D,Data!$A:$A,">="&$A6,Data!$A:$A,"<="&($A6+6),Data!$B:$B,IF($B$2="All","*",$B$2)) | C6: =SUMIFS(Data!$E:$E,Data!$A:$A,">="&$A6,Data!$A:$A,"<="&($A6+6),Data!$B:$B,IF($B$2="All","*",$B$2)) | D6: =SUMIFS(Data!$F:$F,Data!$A:$A,">="&$A6,Data!$A:$A,"<="&($A6+6),Data!$B:$B,IF($B$2="All","*",$B$2)) | E6: =IFERROR(D6/B6,"") | F6: =IFERROR(C6/B6,"") | G6: =SUMIFS(Data!$G:$G,Data!$A:$A,">="&$A6,Data!$A:$A,"<="&($A6+6),Data!$B:$B,IF($B$2="All","*",$B$2)) | H6: =IFERROR(G6/D6,"") | I6: =G6-D6
A7: 46178 | B7: =SUMIFS(Data!$D:$D,Data!$A:$A,">="&$A7,Data!$A:$A,"<="&($A7+6),Data!$B:$B,IF($B$2="All","*",$B$2)) | C7: =SUMIFS(Data!$E:$E,Data!$A:$A,">="&$A7,Data!$A:$A,"<="&($A7+6),Data!$B:$B,IF($B$2="All","*",$B$2)) | D7: =SUMIFS(Data!$F:$F,Data!$A:$A,">="&$A7,Data!$A:$A,"<="&($A7+6),Data!$B:$B,IF($B$2="All","*",$B$2)) | E7: =IFERROR(D7/B7,"") | F7: =IFERROR(C7/B7,"") | G7: =SUMIFS(Data!$G:$G,Data!$A:$A,">="&$A7,Data!$A:$A,"<="&($A7+6),Data!$B:$B,IF($B$2="All","*",$B$2)) | H7: =IFERROR(G7/D7,"") | I7: =G7-D7
A8: 46171 | B8: =SUMIFS(Data!$D:$D,Data!$A:$A,">="&$A8,Data!$A:$A,"<="&($A8+6),Data!$B:$B,IF($B$2="All","*",$B$2)) | C8: =SUMIFS(Data!$E:$E,Data!$A:$A,">="&$A8,Data!$A:$A,"<="&($A8+6),Data!$B:$B,IF($B$2="All","*",$B$2)) | D8: =SUMIFS(Data!$F:$F,Data!$A:$A,">="&$A8,Data!$A:$A,"<="&($A8+6),Data!$B:$B,IF($B$2="All","*",$B$2)) | E8: =IFERROR(D8/B8,"") | F8: =IFERROR(C8/B8,"") | G8: =SUMIFS(Data!$G:$G,Data!$A:$A,">="&$A8,Data!$A:$A,"<="&($A8+6),Data!$B:$B,IF($B$2="All","*",$B$2)) | H8: =IFERROR(G8/D8,"") | I8: =G8-D8
A9: 46164 | B9: =SUMIFS(Data!$D:$D,Data!$A:$A,">="&$A9,Data!$A:$A,"<="&($A9+6),Data!$B:$B,IF($B$2="All","*",$B$2)) | C9: =SUMIFS(Data!$E:$E,Data!$A:$A,">="&$A9,Data!$A:$A,"<="&($A9+6),Data!$B:$B,IF($B$2="All","*",$B$2)) | D9: =SUMIFS(Data!$F:$F,Data!$A:$A,">="&$A9,Data!$A:$A,"<="&($A9+6),Data!$B:$B,IF($B$2="All","*",$B$2)) | E9: =IFERROR(D9/B9,"") | F9: =IFERROR(C9/B9,"") | G9: =SUMIFS(Data!$G:$G,Data!$A:$A,">="&$A9,Data!$A:$A,"<="&($A9+6),Data!$B:$B,IF($B$2="All","*",$B$2)) | H9: =IFERROR(G9/D9,"") | I9: =G9-D9
A10: 46157 | B10: =SUMIFS(Data!$D:$D,Data!$A:$A,">="&$A10,Data!$A:$A,"<="&($A10+6),Data!$B:$B,IF($B$2="All","*",$B$2)) | C10: =SUMIFS(Data!$E:$E,Data!$A:$A,">="&$A10,Data!$A:$A,"<="&($A10+6),Data!$B:$B,IF($B$2="All","*",$B$2)) | D10: =SUMIFS(Data!$F:$F,Data!$A:$A,">="&$A10,Data!$A:$A,"<="&($A10+6),Data!$B:$B,IF($B$2="All","*",$B$2)) | E10: =IFERROR(D10/B10,"") | F10: =IFERROR(C10/B10,"") | G10: =SUMIFS(Data!$G:$G,Data!$A:$A,">="&$A10,Data!$A:$A,"<="&($A10+6),Data!$B:$B,IF($B$2="All","*",$B$2)) | H10: =IFERROR(G10/D10,"") | I10: =G10-D10
A11: 46150 | B11: =SUMIFS(Data!$D:$D,Data!$A:$A,">="&$A11,Data!$A:$A,"<="&($A11+6),Data!$B:$B,IF($B$2="All","*",$B$2)) | C11: =SUMIFS(Data!$E:$E,Data!$A:$A,">="&$A11,Data!$A:$A,"<="&($A11+6),Data!$B:$B,IF($B$2="All","*",$B$2)) | D11: =SUMIFS(Data!$F:$F,Data!$A:$A,">="&$A11,Data!$A:$A,"<="&($A11+6),Data!$B:$B,IF($B$2="All","*",$B$2)) | E11: =IFERROR(D11/B11,"") | F11: =IFERROR(C11/B11,"") | G11: =SUMIFS(Data!$G:$G,Data!$A:$A,">="&$A11,Data!$A:$A,"<="&($A11+6),Data!$B:$B,IF($B$2="All","*",$B$2)) | H11: =IFERROR(G11/D11,"") | I11: =G11-D11
A12: 46143 | B12: =SUMIFS(Data!$D:$D,Data!$A:$A,">="&$A12,Data!$A:$A,"<="&($A12+6),Data!$B:$B,IF($B$2="All","*",$B$2)) | C12: =SUMIFS(Data!$E:$E,Data!$A:$A,">="&$A12,Data!$A:$A,"<="&($A12+6),Data!$B:$B,IF($B$2="All","*",$B$2)) | D12: =SUMIFS(Data!$F:$F,Data!$A:$A,">="&$A12,Data!$A:$A,"<="&($A12+6),Data!$B:$B,IF($B$2="All","*",$B$2)) | E12: =IFERROR(D12/B12,"") | F12: =IFERROR(C12/B12,"") | G12: =SUMIFS(Data!$G:$G,Data!$A:$A,">="&$A12,Data!$A:$A,"<="&($A12+6),Data!$B:$B,IF($B$2="All","*",$B$2)) | H12: =IFERROR(G12/D12,"") | I12: =G12-D12
A13: 46136 | B13: =SUMIFS(Data!$D:$D,Data!$A:$A,">="&$A13,Data!$A:$A,"<="&($A13+6),Data!$B:$B,IF($B$2="All","*",$B$2)) | C13: =SUMIFS(Data!$E:$E,Data!$A:$A,">="&$A13,Data!$A:$A,"<="&($A13+6),Data!$B:$B,IF($B$2="All","*",$B$2)) | D13: =SUMIFS(Data!$F:$F,Data!$A:$A,">="&$A13,Data!$A:$A,"<="&($A13+6),Data!$B:$B,IF($B$2="All","*",$B$2)) | E13: =IFERROR(D13/B13,"") | F13: =IFERROR(C13/B13,"") | G13: =SUMIFS(Data!$G:$G,Data!$A:$A,">="&$A13,Data!$A:$A,"<="&($A13+6),Data!$B:$B,IF($B$2="All","*",$B$2)) | H13: =IFERROR(G13/D13,"") | I13: =G13-D13
A14: 46129 | B14: =SUMIFS(Data!$D:$D,Data!$A:$A,">="&$A14,Data!$A:$A,"<="&($A14+6),Data!$B:$B,IF($B$2="All","*",$B$2)) | C14: =SUMIFS(Data!$E:$E,Data!$A:$A,">="&$A14,Data!$A:$A,"<="&($A14+6),Data!$B:$B,IF($B$2="All","*",$B$2)) | D14: =SUMIFS(Data!$F:$F,Data!$A:$A,">="&$A14,Data!$A:$A,"<="&($A14+6),Data!$B:$B,IF($B$2="All","*",$B$2)) | E14: =IFERROR(D14/B14,"") | F14: =IFERROR(C14/B14,"") | G14: =SUMIFS(Data!$G:$G,Data!$A:$A,">="&$A14,Data!$A:$A,"<="&($A14+6),Data!$B:$B,IF($B$2="All","*",$B$2)) | H14: =IFERROR(G14/D14,"") | I14: =G14-D14
A15: 46122 | B15: =SUMIFS(Data!$D:$D,Data!$A:$A,">="&$A15,Data!$A:$A,"<="&($A15+6),Data!$B:$B,IF($B$2="All","*",$B$2)) | C15: =SUMIFS(Data!$E:$E,Data!$A:$A,">="&$A15,Data!$A:$A,"<="&($A15+6),Data!$B:$B,IF($B$2="All","*",$B$2)) | D15: =SUMIFS(Data!$F:$F,Data!$A:$A,">="&$A15,Data!$A:$A,"<="&($A15+6),Data!$B:$B,IF($B$2="All","*",$B$2)) | E15: =IFERROR(D15/B15,"") | F15: =IFERROR(C15/B15,"") | G15: =SUMIFS(Data!$G:$G,Data!$A:$A,">="&$A15,Data!$A:$A,"<="&($A15+6),Data!$B:$B,IF($B$2="All","*",$B$2)) | H15: =IFERROR(G15/D15,"") | I15: =G15-D15

Sheet Data
A1: =IFERROR(IMPORTDATA("https://ad-suite-production.up.railway.app/sheet-grid?key=uncvrd2026&v=15&sheet="&'Weekly Stats'!$B$3),"") | I1: DateKey | K1: Auto data from the server — don't type here.
I2: =ARRAYFORMULA(IF(LEN(A2:A100000)=0,"",TEXT(A2:A100000,"yyyy-mm-dd")))

Sheet Cohort
A1: =IFERROR(IMPORTDATA("https://ad-suite-production.up.railway.app/cohort-grid?key=uncvrd2026&v=15&sheet="&'Weekly Stats'!$B$3),"") | L1: Auto cohort data from the server (lifetime revenue per subscriber, by age) — don't type here.

Sheet Manual Spend
A1: MANUAL SPEND — type what you spent on OnlyFinder / OnlyGuider / OnlySeeker.
A2: Date | B2: Creator | C2: Platform | D2: Amount ($)
